{"nodes":[{"id":"item_1896","name":"Kenya","category":0,"symbolSize":45,"isCenter":true,"itemId":1896},{"id":"item_1917","name":"Archers Post","category":1,"symbolSize":22,"itemId":1917},{"id":"item_1933","name":"Entasekera","category":1,"symbolSize":22,"itemId":1933},{"id":"item_1943","name":"Isiolo","category":1,"symbolSize":22,"itemId":1943},{"id":"item_1947","name":"Kalacha","category":1,"symbolSize":22,"itemId":1947},{"id":"item_1953","name":"Loita Hills","category":1,"symbolSize":22,"itemId":1953},{"id":"item_1954","name":"Loita Naimina Enkiyio Forest","category":1,"symbolSize":22,"itemId":1954},{"id":"item_1959","name":"Maasai Mara National Reserve","category":1,"symbolSize":22,"itemId":1959},{"id":"item_1968","name":"Mpuaai","category":1,"symbolSize":22,"itemId":1968},{"id":"item_1970","name":"Nairobi","category":1,"symbolSize":22,"itemId":1970},{"id":"item_1976","name":"Olepolos","category":1,"symbolSize":22,"itemId":1976},{"id":"item_1990","name":"Talek","category":1,"symbolSize":22,"itemId":1990},{"id":"item_1999","name":"Turkana South","category":1,"symbolSize":22,"itemId":1999},{"id":"item_7696","name":"Mariasole Pepa's transcript, Tanzania, March 14, 2022","category":2,"symbolSize":16,"itemId":7696},{"id":"item_9924","name":"Locating the Albatross in Women’s Political Participation in Sub-Saharan Africa","category":2,"symbolSize":16,"itemId":9924},{"id":"item_7948","name":"Kidege Changu","category":2,"symbolSize":16,"itemId":7948},{"id":"item_7949","name":"Peas","category":2,"symbolSize":16,"itemId":7949},{"id":"item_7950","name":"Pendo Lako","category":2,"symbolSize":16,"itemId":7950},{"id":"item_7951","name":"Dali Jongea","category":2,"symbolSize":16,"itemId":7951},{"id":"item_7952","name":"Ebyenaku Zino","category":2,"symbolSize":16,"itemId":7952},{"id":"item_7953","name":"Ensi Yafe","category":2,"symbolSize":16,"itemId":7953},{"id":"item_7954","name":"Kidege Mbona Wanisumbua","category":2,"symbolSize":16,"itemId":7954},{"id":"item_7955","name":"Bura Kwetu Hatuna Kazi","category":2,"symbolSize":16,"itemId":7955},{"id":"item_7956","name":"Malaika Nakupenda","category":2,"symbolSize":16,"itemId":7956},{"id":"item_7957","name":"Pete Ni Alama","category":2,"symbolSize":16,"itemId":7957},{"id":"item_7958","name":"Mama Sofia","category":2,"symbolSize":16,"itemId":7958},{"id":"item_7959","name":"Mbiu Ya Mogambo","category":2,"symbolSize":16,"itemId":7959},{"id":"item_7960","name":"Mahaba Yamekwisha","category":2,"symbolSize":16,"itemId":7960},{"id":"item_7961","name":"Nife Nipate Pumzika","category":2,"symbolSize":16,"itemId":7961},{"id":"item_7962","name":"Nipende Mpenzi","category":2,"symbolSize":16,"itemId":7962},{"id":"item_7963","name":"Matilda","category":2,"symbolSize":16,"itemId":7963},{"id":"item_7964","name":"Brazil","category":2,"symbolSize":16,"itemId":7964},{"id":"item_7965","name":"Nalia Jamani","category":2,"symbolSize":16,"itemId":7965},{"id":"item_7966","name":"Bibi Mzuri","category":2,"symbolSize":16,"itemId":7966},{"id":"item_7967","name":"Maria","category":2,"symbolSize":16,"itemId":7967},{"id":"item_7968","name":"Mja Akiteswa","category":2,"symbolSize":16,"itemId":7968},{"id":"item_7969","name":"Majirani","category":2,"symbolSize":16,"itemId":7969},{"id":"item_7970","name":"Nafa Kwa Mahaba","category":2,"symbolSize":16,"itemId":7970},{"id":"item_7971","name":"Sera Rudi","category":2,"symbolSize":16,"itemId":7971},{"id":"item_7972","name":"Nimechoka Nawe Mpenzi","category":2,"symbolSize":16,"itemId":7972},{"id":"item_7973","name":"Nalia Mpenzi","category":2,"symbolSize":16,"itemId":7973},{"id":"item_7974","name":"Rebeka","category":2,"symbolSize":16,"itemId":7974},{"id":"item_7975","name":"Ndizi","category":2,"symbolSize":16,"itemId":7975},{"id":"item_7976","name":"Di Cwynyi","category":2,"symbolSize":16,"itemId":7976},{"id":"item_7977","name":"Maringo","category":2,"symbolSize":16,"itemId":7977},{"id":"item_7978","name":"‘Ee Maria","category":2,"symbolSize":16,"itemId":7978},{"id":"item_7979","name":"Nyanya","category":2,"symbolSize":16,"itemId":7979},{"id":"item_7980","name":"Elia Utalia","category":2,"symbolSize":16,"itemId":7980},{"id":"item_7981","name":"Utakuwa Mvivu","category":2,"symbolSize":16,"itemId":7981},{"id":"item_7982","name":"Hukuni Jail","category":2,"symbolSize":16,"itemId":7982},{"id":"item_7983","name":"Pita Mbali","category":2,"symbolSize":16,"itemId":7983},{"id":"item_7984","name":"Siri Yangu","category":2,"symbolSize":16,"itemId":7984},{"id":"item_7985","name":"Jasho","category":2,"symbolSize":16,"itemId":7985}],"edges":[{"source":"item_1917","target":"item_1896","name":"Is Part Of"},{"source":"item_1933","target":"item_1896","name":"Is Part Of"},{"source":"item_1943","target":"item_1896","name":"Is Part Of"},{"source":"item_1947","target":"item_1896","name":"Is Part Of"},{"source":"item_1953","target":"item_1896","name":"Is Part Of"},{"source":"item_1954","target":"item_1896","name":"Is Part Of"},{"source":"item_1959","target":"item_1896","name":"Is Part Of"},{"source":"item_1968","target":"item_1896","name":"Is Part Of"},{"source":"item_1970","target":"item_1896","name":"Is Part Of"},{"source":"item_1976","target":"item_1896","name":"Is Part Of"},{"source":"item_1990","target":"item_1896","name":"Is Part Of"},{"source":"item_1999","target":"item_1896","name":"Is Part Of"},{"source":"item_7696","target":"item_1896","name":"references"},{"source":"item_9924","target":"item_1896","name":"references"},{"source":"item_7948","target":"item_1896","name":"references"},{"source":"item_7949","target":"item_1896","name":"references"},{"source":"item_7950","target":"item_1896","name":"references"},{"source":"item_7951","target":"item_1896","name":"references"},{"source":"item_7952","target":"item_1896","name":"references"},{"source":"item_7953","target":"item_1896","name":"references"},{"source":"item_7954","target":"item_1896","name":"references"},{"source":"item_7955","target":"item_1896","name":"references"},{"source":"item_7956","target":"item_1896","name":"references"},{"source":"item_7957","target":"item_1896","name":"references"},{"source":"item_7958","target":"item_1896","name":"references"},{"source":"item_7959","target":"item_1896","name":"references"},{"source":"item_7960","target":"item_1896","name":"references"},{"source":"item_7961","target":"item_1896","name":"references"},{"source":"item_7962","target":"item_1896","name":"references"},{"source":"item_7963","target":"item_1896","name":"references"},{"source":"item_7964","target":"item_1896","name":"references"},{"source":"item_7965","target":"item_1896","name":"references"},{"source":"item_7966","target":"item_1896","name":"references"},{"source":"item_7967","target":"item_1896","name":"references"},{"source":"item_7968","target":"item_1896","name":"references"},{"source":"item_7969","target":"item_1896","name":"references"},{"source":"item_7970","target":"item_1896","name":"references"},{"source":"item_7971","target":"item_1896","name":"references"},{"source":"item_7972","target":"item_1896","name":"references"},{"source":"item_7973","target":"item_1896","name":"references"},{"source":"item_7974","target":"item_1896","name":"references"},{"source":"item_7975","target":"item_1896","name":"references"},{"source":"item_7976","target":"item_1896","name":"references"},{"source":"item_7977","target":"item_1896","name":"references"},{"source":"item_7978","target":"item_1896","name":"references"},{"source":"item_7979","target":"item_1896","name":"references"},{"source":"item_7980","target":"item_1896","name":"references"},{"source":"item_7981","target":"item_1896","name":"references"},{"source":"item_7982","target":"item_1896","name":"references"},{"source":"item_7983","target":"item_1896","name":"references"},{"source":"item_7984","target":"item_1896","name":"references"},{"source":"item_7985","target":"item_1896","name":"references"}],"categories":[{"name":"Location"},{"name":"Linked Item"},{"name":"Research Item"}],"stats":{"maxStrength":0.0,"maxFreqPct":0}}