{"nodes":[{"id":"item_9271","name":"Bianca: The Other African in Othello","category":0,"symbolSize":45,"isCenter":true,"itemId":9271},{"id":"resource_2090","name":"Books","category":1,"symbolSize":22,"itemId":2090},{"id":"resource_2965","name":"Othello","category":1,"symbolSize":22,"itemId":2965},{"id":"resource_2511","name":"Bianca","category":1,"symbolSize":22,"itemId":2511},{"id":"resource_3061","name":"Shakespeare","category":1,"symbolSize":22,"itemId":3061},{"id":"resource_2959","name":"Origin","category":1,"symbolSize":22,"itemId":2959},{"id":"resource_2546","name":"Chapter","category":1,"symbolSize":22,"itemId":2546},{"id":"resource_229","name":"Donawerth, Jane","category":2,"symbolSize":22,"itemId":229},{"id":"resource_1324","name":"Routledge","category":2,"symbolSize":22,"itemId":1324},{"id":"resource_1796","name":"Travelling Knowledge and Trans*textuality: African Sources in Shakespearean Drama","category":3,"symbolSize":22,"itemId":1796},{"id":"resource_1973","name":"New York","category":4,"symbolSize":22,"itemId":1973},{"id":"resource_1912","name":"United States of America","category":4,"symbolSize":22,"itemId":1912},{"id":"resource_10303","name":"EXC2052/1 Africa Multiple, DFG Project number 390713894","category":5,"symbolSize":22,"itemId":10303},{"id":"resource_10300","name":"Digital","category":6,"symbolSize":22,"itemId":10300},{"id":"resource_7641","name":"digitized other analog","category":6,"symbolSize":22,"itemId":7641},{"id":"item_7392","name":"Volume 8: Yoruba Architecture and Wall Painting. Digitaler Scan im Beier-Nachlass","category":7,"symbolSize":16,"itemId":7392},{"id":"item_7393","name":"Abschrift von das Buch: Leopold Sedar Senghor (befindet sich in die National Archives, Canberra)","category":7,"symbolSize":16,"itemId":7393},{"id":"item_7394","name":"Museum of Antiquities in Osogbo: A Project of the Institute of African Studies, University of Ife","category":7,"symbolSize":16,"itemId":7394},{"id":"item_7395","name":"The Rietbeg Museum and the Antiquities Dealer","category":7,"symbolSize":16,"itemId":7395},{"id":"item_7396","name":"Collection of Ulli and Georgina Beier","category":7,"symbolSize":16,"itemId":7396},{"id":"item_9441","name":"British Library_Voyages to Guinea","category":7,"symbolSize":16,"itemId":9441},{"id":"item_9442","name":"British Library_Voyages to Guinea","category":7,"symbolSize":16,"itemId":9442},{"id":"item_7405","name":"Drei Buchdeckel, die von Georgina Beier gestaltet wurden, in einer schwarzen Mappe","category":7,"symbolSize":16,"itemId":7405},{"id":"item_9230","name":"West African Folktales","category":7,"symbolSize":16,"itemId":9230},{"id":"item_8207","name":"Untitled","category":7,"symbolSize":16,"itemId":8207},{"id":"item_9261","name":"The Anglo-African Commonwealth: Political friction and cultural fusion","category":7,"symbolSize":16,"itemId":9261},{"id":"item_9554","name":"Book Binding_British Library","category":7,"symbolSize":16,"itemId":9554},{"id":"item_9236","name":"Drama at Sea: A New Look at Shakespeare on the Dragon, 1607-08","category":7,"symbolSize":16,"itemId":9236},{"id":"item_7574","name":"Erste Seite des Kapitels Races of the World aus dem Buch Modern Pictoral Atlas von Newnes (1939, 113)","category":7,"symbolSize":16,"itemId":7574},{"id":"item_7575","name":"Seite aus dem Buch Modern Pictorial Atlas von Newnes (1939)","category":7,"symbolSize":16,"itemId":7575},{"id":"item_9661","name":"Book Binding","category":7,"symbolSize":16,"itemId":9661},{"id":"item_9662","name":"Book Binding","category":7,"symbolSize":16,"itemId":9662},{"id":"item_9248","name":"Tran*stextuality in William Shakespeare's Othello: Italian, West African and English Encounters","category":7,"symbolSize":16,"itemId":9248},{"id":"item_9250","name":"Othello and Africa: Postcolonialism Reconsidered","category":7,"symbolSize":16,"itemId":9250},{"id":"item_9255","name":"Othello the Complete Gentleman: An African Folkloric Interpretation","category":7,"symbolSize":16,"itemId":9255},{"id":"item_9234","name":"Collaborating with a Dead Man: The Cultural Politics of Ahmed Yerima's Otaelo","category":7,"symbolSize":16,"itemId":9234},{"id":"item_9266","name":"Othello and the Narrative of Africa","category":7,"symbolSize":16,"itemId":9266},{"id":"item_9238","name":"From Ògún to Othello: (Re)Acquainting Yoruba Myth and Shakespeare’s Moo","category":7,"symbolSize":16,"itemId":9238},{"id":"item_9247","name":"Othello's African American Progeny","category":7,"symbolSize":16,"itemId":9247},{"id":"item_9237","name":"Charlotte Lennox / Karl Simrock Two pioneers in Shakespeare source studies","category":7,"symbolSize":16,"itemId":9237},{"id":"item_9243","name":"Origins and Transformations A little introduction to the development of Shakespeare source studies","category":7,"symbolSize":16,"itemId":9243},{"id":"item_9244","name":"Violence and Xenophobia in South Africa: Shakespeare, Thomas Mofolo's Chaka, and Welcome Msomi's uMabatha: the Zulu Macbeth","category":7,"symbolSize":16,"itemId":9244},{"id":"item_9245","name":"Parody of the Shakespearean Fool Tradition in an African Society","category":7,"symbolSize":16,"itemId":9245},{"id":"item_9246","name":"Translation as Rewriting: Cultural Theoretical Appraisal of Shakespeare’s Macbeth in the Ewe language of West Africa","category":7,"symbolSize":16,"itemId":9246},{"id":"item_9249","name":"CALIBAN ANSWERS PROSPERO: The Dialogue between Western and African Literature","category":7,"symbolSize":16,"itemId":9249}],"edges":[{"source":"item_9271","target":"resource_2090","name":"Subject"},{"source":"item_9271","target":"resource_2965","name":"Subject"},{"source":"item_9271","target":"resource_2511","name":"Subject"},{"source":"item_9271","target":"resource_3061","name":"Subject"},{"source":"item_9271","target":"resource_2959","name":"Subject"},{"source":"item_9271","target":"resource_2546","name":"Subject"},{"source":"item_9271","target":"resource_229","name":"author"},{"source":"item_9271","target":"resource_1324","name":"publisher"},{"source":"item_9271","target":"resource_1796","name":"Is Part Of"},{"source":"item_9271","target":"resource_1973","name":"Spatial Coverage"},{"source":"item_9271","target":"resource_1912","name":"Spatial Coverage"},{"source":"item_9271","target":"resource_10303","name":"is funded by"},{"source":"item_9271","target":"resource_10300","name":"Format"},{"source":"item_9271","target":"resource_7641","name":"Format"},{"source":"item_7392","target":"resource_2090","name":"Subject","isShared":true},{"source":"item_7393","target":"resource_2090","name":"Subject","isShared":true},{"source":"item_7394","target":"resource_2090","name":"Subject","isShared":true},{"source":"item_7395","target":"resource_2090","name":"Subject","isShared":true},{"source":"item_7396","target":"resource_2090","name":"Subject","isShared":true},{"source":"item_9441","target":"resource_2090","name":"Subject","isShared":true},{"source":"item_9441","target":"resource_1796","name":"Is Part Of","isShared":true},{"source":"item_9442","target":"resource_2090","name":"Subject","isShared":true},{"source":"item_9442","target":"resource_1796","name":"Is Part Of","isShared":true},{"source":"item_7405","target":"resource_2090","name":"Subject","isShared":true},{"source":"item_9230","target":"resource_2090","name":"Subject","isShared":true},{"source":"item_9230","target":"resource_1796","name":"Is Part Of","isShared":true},{"source":"item_8207","target":"resource_2090","name":"Subject","isShared":true},{"source":"item_9261","target":"resource_2090","name":"Subject","isShared":true},{"source":"item_9261","target":"resource_1796","name":"Is Part Of","isShared":true},{"source":"item_9554","target":"resource_2090","name":"Subject","isShared":true},{"source":"item_9554","target":"resource_1796","name":"Is Part Of","isShared":true},{"source":"item_9236","target":"resource_2090","name":"Subject","isShared":true},{"source":"item_9236","target":"resource_3061","name":"Subject","isShared":true},{"source":"item_9236","target":"resource_2546","name":"Subject","isShared":true},{"source":"item_9236","target":"resource_1796","name":"Is Part Of","isShared":true},{"source":"item_7574","target":"resource_2090","name":"Subject","isShared":true},{"source":"item_7575","target":"resource_2090","name":"Subject","isShared":true},{"source":"item_9661","target":"resource_2090","name":"Subject","isShared":true},{"source":"item_9661","target":"resource_1796","name":"Is Part Of","isShared":true},{"source":"item_9662","target":"resource_2090","name":"Subject","isShared":true},{"source":"item_9662","target":"resource_1796","name":"Is Part Of","isShared":true},{"source":"item_9248","target":"resource_3061","name":"Subject","isShared":true},{"source":"item_9248","target":"resource_2965","name":"Subject","isShared":true},{"source":"item_9248","target":"resource_1796","name":"Is Part Of","isShared":true},{"source":"item_9250","target":"resource_3061","name":"Subject","isShared":true},{"source":"item_9250","target":"resource_2965","name":"Subject","isShared":true},{"source":"item_9250","target":"resource_1796","name":"Is Part Of","isShared":true},{"source":"item_9250","target":"resource_1912","name":"Spatial Coverage","isShared":true},{"source":"item_9255","target":"resource_3061","name":"Subject","isShared":true},{"source":"item_9255","target":"resource_2965","name":"Subject","isShared":true},{"source":"item_9255","target":"resource_1796","name":"Is Part Of","isShared":true},{"source":"item_9255","target":"resource_1912","name":"Spatial Coverage","isShared":true},{"source":"item_9234","target":"resource_3061","name":"Subject","isShared":true},{"source":"item_9234","target":"resource_2965","name":"Subject","isShared":true},{"source":"item_9234","target":"resource_1796","name":"Is Part Of","isShared":true},{"source":"item_9266","target":"resource_3061","name":"Subject","isShared":true},{"source":"item_9266","target":"resource_2965","name":"Subject","isShared":true},{"source":"item_9266","target":"resource_1796","name":"Is Part Of","isShared":true},{"source":"item_9238","target":"resource_3061","name":"Subject","isShared":true},{"source":"item_9238","target":"resource_2965","name":"Subject","isShared":true},{"source":"item_9238","target":"resource_1796","name":"Is Part Of","isShared":true},{"source":"item_9238","target":"resource_1912","name":"Spatial Coverage","isShared":true},{"source":"item_9247","target":"resource_2965","name":"Subject","isShared":true},{"source":"item_9247","target":"resource_1796","name":"Is Part Of","isShared":true},{"source":"item_9247","target":"resource_1912","name":"Spatial Coverage","isShared":true},{"source":"item_9234","target":"resource_3061","name":"Subject","isShared":true},{"source":"item_9234","target":"resource_2965","name":"Subject","isShared":true},{"source":"item_9234","target":"resource_1796","name":"Is Part Of","isShared":true},{"source":"item_9236","target":"resource_2090","name":"Subject","isShared":true},{"source":"item_9236","target":"resource_3061","name":"Subject","isShared":true},{"source":"item_9236","target":"resource_2546","name":"Subject","isShared":true},{"source":"item_9236","target":"resource_1796","name":"Is Part Of","isShared":true},{"source":"item_9237","target":"resource_3061","name":"Subject","isShared":true},{"source":"item_9237","target":"resource_1796","name":"Is Part Of","isShared":true},{"source":"item_9238","target":"resource_3061","name":"Subject","isShared":true},{"source":"item_9238","target":"resource_2965","name":"Subject","isShared":true},{"source":"item_9238","target":"resource_1796","name":"Is Part Of","isShared":true},{"source":"item_9238","target":"resource_1912","name":"Spatial Coverage","isShared":true},{"source":"item_9243","target":"resource_3061","name":"Subject","isShared":true},{"source":"item_9243","target":"resource_1796","name":"Is Part Of","isShared":true},{"source":"item_9244","target":"resource_3061","name":"Subject","isShared":true},{"source":"item_9244","target":"resource_1796","name":"Is Part Of","isShared":true},{"source":"item_9244","target":"resource_1912","name":"Spatial Coverage","isShared":true},{"source":"item_9245","target":"resource_3061","name":"Subject","isShared":true},{"source":"item_9245","target":"resource_1796","name":"Is Part Of","isShared":true},{"source":"item_9246","target":"resource_3061","name":"Subject","isShared":true},{"source":"item_9246","target":"resource_1796","name":"Is Part Of","isShared":true},{"source":"item_9248","target":"resource_3061","name":"Subject","isShared":true},{"source":"item_9248","target":"resource_2965","name":"Subject","isShared":true},{"source":"item_9248","target":"resource_1796","name":"Is Part Of","isShared":true},{"source":"item_9249","target":"resource_3061","name":"Subject","isShared":true},{"source":"item_9249","target":"resource_1796","name":"Is Part Of","isShared":true},{"source":"item_9249","target":"resource_1912","name":"Spatial Coverage","isShared":true}],"categories":[{"name":"Item"},{"name":"Subject"},{"name":"Contributor"},{"name":"Project"},{"name":"Location"},{"name":"Institution"},{"name":"Genre"},{"name":"Shared Item"}]}