{"nodes":[{"id":"item_9567","name":"Letters Henry Yelverton","category":0,"symbolSize":45,"isCenter":true,"itemId":9567},{"id":"resource_215","name":"Aboluwade, Ifeoluwa","category":1,"symbolSize":22,"itemId":215,"freqPct":6.2},{"id":"resource_2243","name":"Manuscripts","category":2,"symbolSize":22,"itemId":2243,"freqPct":6.2},{"id":"resource_2024","name":"Early modern, 1500-1700","category":2,"symbolSize":22,"itemId":2024,"freqPct":6.2},{"id":"resource_2237","name":"Literature","category":2,"symbolSize":22,"itemId":2237,"freqPct":6.2},{"id":"resource_2057","name":"Africa","category":2,"symbolSize":22,"itemId":2057,"freqPct":9.3},{"id":"resource_2234","name":"Letters","category":2,"symbolSize":22,"itemId":2234,"freqPct":2.1},{"id":"resource_2752","name":"Handwritten","category":2,"symbolSize":22,"itemId":2752,"freqPct":5.0},{"id":"resource_2657","name":"England","category":2,"symbolSize":22,"itemId":2657,"freqPct":6.2},{"id":"resource_2825","name":"Knowledge","category":2,"symbolSize":22,"itemId":2825,"freqPct":6.6},{"id":"resource_1796","name":"Travelling Knowledge and Trans*textuality: African Sources in Shakespearean Drama","category":3,"symbolSize":22,"itemId":1796,"freqPct":8.2},{"id":"resource_1956","name":"London","category":4,"symbolSize":22,"itemId":1956,"freqPct":6.2},{"id":"resource_10303","name":"EXC2052/1 Africa Multiple, DFG Project number 390713894","category":5,"symbolSize":22,"itemId":10303,"freqPct":45.3},{"id":"resource_10300","name":"Digital","category":6,"symbolSize":22,"itemId":10300,"freqPct":32.2},{"id":"resource_7641","name":"digitized other analog","category":6,"symbolSize":22,"itemId":7641,"freqPct":16.6},{"id":"item_9528","name":"Letters Sr Francis Drake","category":7,"symbolSize":16,"itemId":9528,"strength":31.15,"sharedCount":11},{"id":"item_9530","name":"Letters Sr Francis Drake","category":7,"symbolSize":16,"itemId":9530,"strength":31.15,"sharedCount":11},{"id":"item_9531","name":"Letters Sr Francis Drake","category":7,"symbolSize":16,"itemId":9531,"strength":31.15,"sharedCount":11},{"id":"item_9532","name":"Letters Sr Francis Drake","category":7,"symbolSize":16,"itemId":9532,"strength":31.15,"sharedCount":11},{"id":"item_9533","name":"Letters Sr Francis Drake","category":7,"symbolSize":16,"itemId":9533,"strength":31.15,"sharedCount":11},{"id":"item_9534","name":"Letters Sr Francis Drake","category":7,"symbolSize":16,"itemId":9534,"strength":31.15,"sharedCount":11},{"id":"item_9535","name":"Letters Sr Francis Drake","category":7,"symbolSize":16,"itemId":9535,"strength":31.15,"sharedCount":11},{"id":"item_9536","name":"Letters Sr Francis Drake","category":7,"symbolSize":16,"itemId":9536,"strength":31.15,"sharedCount":11},{"id":"item_9555","name":"Letters Henry Yelverton","category":7,"symbolSize":16,"itemId":9555,"strength":31.15,"sharedCount":11},{"id":"item_9556","name":"Letters Henry Yelverton","category":7,"symbolSize":16,"itemId":9556,"strength":31.15,"sharedCount":11},{"id":"item_9557","name":"Letters Henry Yelverton","category":7,"symbolSize":16,"itemId":9557,"strength":31.15,"sharedCount":11},{"id":"item_9558","name":"Letters Henry Yelverton","category":7,"symbolSize":16,"itemId":9558,"strength":31.15,"sharedCount":11},{"id":"item_9559","name":"Letters Henry Yelverton","category":7,"symbolSize":16,"itemId":9559,"strength":31.15,"sharedCount":11},{"id":"item_9560","name":"Letters Henry Yelverton","category":7,"symbolSize":16,"itemId":9560,"strength":31.15,"sharedCount":11},{"id":"item_9561","name":"Letters Henry Yelverton","category":7,"symbolSize":16,"itemId":9561,"strength":31.15,"sharedCount":11},{"id":"item_9562","name":"Letters Henry Yelverton","category":7,"symbolSize":16,"itemId":9562,"strength":31.15,"sharedCount":11},{"id":"item_9563","name":"Letters Henry Yelverton","category":7,"symbolSize":16,"itemId":9563,"strength":31.15,"sharedCount":11},{"id":"item_9564","name":"Letters Henry Yelverton","category":7,"symbolSize":16,"itemId":9564,"strength":31.15,"sharedCount":11},{"id":"item_9565","name":"Letters Henry Yelverton","category":7,"symbolSize":16,"itemId":9565,"strength":31.15,"sharedCount":11},{"id":"item_9566","name":"Letters Henry Yelverton","category":7,"symbolSize":16,"itemId":9566,"strength":31.15,"sharedCount":11},{"id":"item_9568","name":"Letters Henry Yelverton","category":7,"symbolSize":16,"itemId":9568,"strength":31.15,"sharedCount":11},{"id":"item_9569","name":"Letters Henry Yelverton","category":7,"symbolSize":16,"itemId":9569,"strength":31.15,"sharedCount":11},{"id":"item_9570","name":"Letters Henry Yelverton","category":7,"symbolSize":16,"itemId":9570,"strength":31.15,"sharedCount":11},{"id":"item_9379","name":"Untitled","category":7,"symbolSize":16,"itemId":9379,"strength":27.29,"sharedCount":10},{"id":"item_9381","name":"Untitled","category":7,"symbolSize":16,"itemId":9381,"strength":27.29,"sharedCount":10},{"id":"item_9407","name":"Court Records Moone v Bury REQ 2/64/113","category":7,"symbolSize":16,"itemId":9407,"strength":27.29,"sharedCount":10},{"id":"item_9408","name":"Court Records Moone v Bury REQ 2/64/113","category":7,"symbolSize":16,"itemId":9408,"strength":27.29,"sharedCount":10},{"id":"item_9409","name":"Court Records Moone v Bury REQ 2/64/113","category":7,"symbolSize":16,"itemId":9409,"strength":27.29,"sharedCount":10},{"id":"item_9410","name":"Court Records Moone v Bury REQ 2/64/113","category":7,"symbolSize":16,"itemId":9410,"strength":27.29,"sharedCount":10},{"id":"item_9411","name":"Court Records Moone v Bury REQ 2/64/113","category":7,"symbolSize":16,"itemId":9411,"strength":27.29,"sharedCount":10},{"id":"item_9412","name":"Court Records Moone v Bury REQ 2/64/113","category":7,"symbolSize":16,"itemId":9412,"strength":27.29,"sharedCount":10},{"id":"item_9413","name":"Court Records Moone v Bury REQ 2/64/113","category":7,"symbolSize":16,"itemId":9413,"strength":27.29,"sharedCount":10},{"id":"item_9414","name":"Court Records Moone v Bury REQ 2/64/113","category":7,"symbolSize":16,"itemId":9414,"strength":27.29,"sharedCount":10},{"id":"item_9415","name":"Court Records Moone v Bury REQ 2/64/113","category":7,"symbolSize":16,"itemId":9415,"strength":27.29,"sharedCount":10},{"id":"item_9416","name":"Court Records Moone v Bury REQ 2/64/113","category":7,"symbolSize":16,"itemId":9416,"strength":27.29,"sharedCount":10},{"id":"item_9417","name":"Court Records Shardelowe v Crowefutt REQ 2/64/116","category":7,"symbolSize":16,"itemId":9417,"strength":27.29,"sharedCount":10},{"id":"item_9418","name":"Court Records Shardelowe v Crowefutt REQ 2/64/116","category":7,"symbolSize":16,"itemId":9418,"strength":27.29,"sharedCount":10},{"id":"item_9419","name":"Court Records Shardelowe v Crowefutt REQ 2/64/116","category":7,"symbolSize":16,"itemId":9419,"strength":27.29,"sharedCount":10},{"id":"item_9420","name":"Court Records Kympton v Spencer REQ 2/64/117","category":7,"symbolSize":16,"itemId":9420,"strength":27.29,"sharedCount":10},{"id":"item_9421","name":"Court Records Kympton v Spencer REQ 2/64/117","category":7,"symbolSize":16,"itemId":9421,"strength":27.29,"sharedCount":10},{"id":"item_9422","name":"Court Records Kympton v Spencer REQ 2/64/117","category":7,"symbolSize":16,"itemId":9422,"strength":27.29,"sharedCount":10},{"id":"item_9423","name":"Court Records Kympton v Spencer REQ 2/64/117","category":7,"symbolSize":16,"itemId":9423,"strength":27.29,"sharedCount":10},{"id":"item_9424","name":"Court Records Wilson v Atkins \\tREQ 2/64/22","category":7,"symbolSize":16,"itemId":9424,"strength":27.29,"sharedCount":10},{"id":"item_9425","name":"Court Records Wilson v Atkins \\tREQ 2/64/22","category":7,"symbolSize":16,"itemId":9425,"strength":27.29,"sharedCount":10},{"id":"item_9426","name":"Court Records Wilson v Atkins \\tREQ 2/64/22","category":7,"symbolSize":16,"itemId":9426,"strength":27.29,"sharedCount":10},{"id":"item_9427","name":"Court Records Isham v Saye REQ 2/64/21","category":7,"symbolSize":16,"itemId":9427,"strength":27.29,"sharedCount":10},{"id":"item_9428","name":"Court Records Isham v Saye REQ 2/64/21","category":7,"symbolSize":16,"itemId":9428,"strength":27.29,"sharedCount":10},{"id":"item_9429","name":"Court Records Isham v Saye REQ 2/64/21","category":7,"symbolSize":16,"itemId":9429,"strength":27.29,"sharedCount":10},{"id":"item_9430","name":"Court Records Isham v Saye REQ 2/64/21","category":7,"symbolSize":16,"itemId":9430,"strength":27.29,"sharedCount":10},{"id":"item_9431","name":"Court Records Isham v Saye REQ 2/64/21","category":7,"symbolSize":16,"itemId":9431,"strength":27.29,"sharedCount":10},{"id":"item_9432","name":"Court Records Isham v Saye REQ 2/64/21","category":7,"symbolSize":16,"itemId":9432,"strength":27.29,"sharedCount":10},{"id":"item_9433","name":"Court Records Isham v Saye REQ 2/64/21","category":7,"symbolSize":16,"itemId":9433,"strength":27.29,"sharedCount":10},{"id":"item_9434","name":"Court Records Isham v Saye REQ 2/64/21","category":7,"symbolSize":16,"itemId":9434,"strength":27.29,"sharedCount":10},{"id":"item_9435","name":"Court Records Hunt v Elmam  \\tREQ 2/64/23","category":7,"symbolSize":16,"itemId":9435,"strength":27.29,"sharedCount":10},{"id":"item_9436","name":"Scarlet Red Cloth and Drapery","category":7,"symbolSize":16,"itemId":9436,"strength":27.29,"sharedCount":10},{"id":"item_9437","name":"Scarlet Red Cloth and Drapery","category":7,"symbolSize":16,"itemId":9437,"strength":27.29,"sharedCount":10},{"id":"item_9438","name":"Scarlet Red Cloth and Drapery","category":7,"symbolSize":16,"itemId":9438,"strength":27.29,"sharedCount":10},{"id":"item_9439","name":"Scarlet Red Cloth and Drapery","category":7,"symbolSize":16,"itemId":9439,"strength":27.29,"sharedCount":10},{"id":"item_9443","name":"British Library_English Exploration and Trade","category":7,"symbolSize":16,"itemId":9443,"strength":27.29,"sharedCount":10},{"id":"item_9444","name":"British Library_English Exploration and Trade","category":7,"symbolSize":16,"itemId":9444,"strength":27.29,"sharedCount":10}],"edges":[{"source":"item_9567","target":"resource_215","name":"collector"},{"source":"item_9567","target":"resource_2243","name":"Subject"},{"source":"item_9567","target":"resource_2024","name":"Subject"},{"source":"item_9567","target":"resource_2237","name":"Subject"},{"source":"item_9567","target":"resource_2057","name":"Subject"},{"source":"item_9567","target":"resource_2234","name":"Subject"},{"source":"item_9567","target":"resource_2752","name":"Subject"},{"source":"item_9567","target":"resource_2657","name":"Subject"},{"source":"item_9567","target":"resource_2825","name":"Subject"},{"source":"item_9567","target":"resource_1796","name":"Is Part Of"},{"source":"item_9567","target":"resource_1956","name":"Spatial Coverage"},{"source":"item_9567","target":"resource_10303","name":"is funded by"},{"source":"item_9567","target":"resource_10300","name":"Format"},{"source":"item_9567","target":"resource_7641","name":"Format"},{"source":"item_9528","target":"resource_2243","name":"Subject","isShared":true,"idf":2.79,"freqPct":6.2},{"source":"item_9528","target":"resource_2024","name":"Subject","isShared":true,"idf":2.79,"freqPct":6.2},{"source":"item_9528","target":"resource_2237","name":"Subject","isShared":true,"idf":2.78,"freqPct":6.2},{"source":"item_9528","target":"resource_2057","name":"Subject","isShared":true,"idf":2.37,"freqPct":9.3},{"source":"item_9528","target":"resource_2234","name":"Subject","isShared":true,"idf":3.86,"freqPct":2.1},{"source":"item_9528","target":"resource_2752","name":"Subject","isShared":true,"idf":3.0,"freqPct":5.0},{"source":"item_9528","target":"resource_2657","name":"Subject","isShared":true,"idf":2.78,"freqPct":6.2},{"source":"item_9528","target":"resource_2825","name":"Subject","isShared":true,"idf":2.71,"freqPct":6.6},{"source":"item_9528","target":"resource_215","name":"collector","isShared":true,"idf":2.79,"freqPct":6.2},{"source":"item_9528","target":"resource_1796","name":"Is Part Of","isShared":true,"idf":2.5,"freqPct":8.2},{"source":"item_9528","target":"resource_1956","name":"Spatial Coverage","isShared":true,"idf":2.78,"freqPct":6.2},{"source":"item_9530","target":"resource_2243","name":"Subject","isShared":true,"idf":2.79,"freqPct":6.2},{"source":"item_9530","target":"resource_2024","name":"Subject","isShared":true,"idf":2.79,"freqPct":6.2},{"source":"item_9530","target":"resource_2237","name":"Subject","isShared":true,"idf":2.78,"freqPct":6.2},{"source":"item_9530","target":"resource_2057","name":"Subject","isShared":true,"idf":2.37,"freqPct":9.3},{"source":"item_9530","target":"resource_2234","name":"Subject","isShared":true,"idf":3.86,"freqPct":2.1},{"source":"item_9530","target":"resource_2752","name":"Subject","isShared":true,"idf":3.0,"freqPct":5.0},{"source":"item_9530","target":"resource_2657","name":"Subject","isShared":true,"idf":2.78,"freqPct":6.2},{"source":"item_9530","target":"resource_2825","name":"Subject","isShared":true,"idf":2.71,"freqPct":6.6},{"source":"item_9530","target":"resource_215","name":"collector","isShared":true,"idf":2.79,"freqPct":6.2},{"source":"item_9530","target":"resource_1796","name":"Is Part Of","isShared":true,"idf":2.5,"freqPct":8.2},{"source":"item_9530","target":"resource_1956","name":"Spatial Coverage","isShared":true,"idf":2.78,"freqPct":6.2},{"source":"item_9531","target":"resource_2243","name":"Subject","isShared":true,"idf":2.79,"freqPct":6.2},{"source":"item_9531","target":"resource_2024","name":"Subject","isShared":true,"idf":2.79,"freqPct":6.2},{"source":"item_9531","target":"resource_2237","name":"Subject","isShared":true,"idf":2.78,"freqPct":6.2},{"source":"item_9531","target":"resource_2057","name":"Subject","isShared":true,"idf":2.37,"freqPct":9.3},{"source":"item_9531","target":"resource_2234","name":"Subject","isShared":true,"idf":3.86,"freqPct":2.1},{"source":"item_9531","target":"resource_2752","name":"Subject","isShared":true,"idf":3.0,"freqPct":5.0},{"source":"item_9531","target":"resource_2657","name":"Subject","isShared":true,"idf":2.78,"freqPct":6.2},{"source":"item_9531","target":"resource_2825","name":"Subject","isShared":true,"idf":2.71,"freqPct":6.6},{"source":"item_9531","target":"resource_215","name":"collector","isShared":true,"idf":2.79,"freqPct":6.2},{"source":"item_9531","target":"resource_1796","name":"Is Part Of","isShared":true,"idf":2.5,"freqPct":8.2},{"source":"item_9531","target":"resource_1956","name":"Spatial Coverage","isShared":true,"idf":2.78,"freqPct":6.2},{"source":"item_9532","target":"resource_2243","name":"Subject","isShared":true,"idf":2.79,"freqPct":6.2},{"source":"item_9532","target":"resource_2024","name":"Subject","isShared":true,"idf":2.79,"freqPct":6.2},{"source":"item_9532","target":"resource_2237","name":"Subject","isShared":true,"idf":2.78,"freqPct":6.2},{"source":"item_9532","target":"resource_2057","name":"Subject","isShared":true,"idf":2.37,"freqPct":9.3},{"source":"item_9532","target":"resource_2234","name":"Subject","isShared":true,"idf":3.86,"freqPct":2.1},{"source":"item_9532","target":"resource_2752","name":"Subject","isShared":true,"idf":3.0,"freqPct":5.0},{"source":"item_9532","target":"resource_2657","name":"Subject","isShared":true,"idf":2.78,"freqPct":6.2},{"source":"item_9532","target":"resource_2825","name":"Subject","isShared":true,"idf":2.71,"freqPct":6.6},{"source":"item_9532","target":"resource_215","name":"collector","isShared":true,"idf":2.79,"freqPct":6.2},{"source":"item_9532","target":"resource_1796","name":"Is Part Of","isShared":true,"idf":2.5,"freqPct":8.2},{"source":"item_9532","target":"resource_1956","name":"Spatial Coverage","isShared":true,"idf":2.78,"freqPct":6.2},{"source":"item_9533","target":"resource_2243","name":"Subject","isShared":true,"idf":2.79,"freqPct":6.2},{"source":"item_9533","target":"resource_2024","name":"Subject","isShared":true,"idf":2.79,"freqPct":6.2},{"source":"item_9533","target":"resource_2237","name":"Subject","isShared":true,"idf":2.78,"freqPct":6.2},{"source":"item_9533","target":"resource_2057","name":"Subject","isShared":true,"idf":2.37,"freqPct":9.3},{"source":"item_9533","target":"resource_2234","name":"Subject","isShared":true,"idf":3.86,"freqPct":2.1},{"source":"item_9533","target":"resource_2752","name":"Subject","isShared":true,"idf":3.0,"freqPct":5.0},{"source":"item_9533","target":"resource_2657","name":"Subject","isShared":true,"idf":2.78,"freqPct":6.2},{"source":"item_9533","target":"resource_2825","name":"Subject","isShared":true,"idf":2.71,"freqPct":6.6},{"source":"item_9533","target":"resource_215","name":"collector","isShared":true,"idf":2.79,"freqPct":6.2},{"source":"item_9533","target":"resource_1796","name":"Is Part Of","isShared":true,"idf":2.5,"freqPct":8.2},{"source":"item_9533","target":"resource_1956","name":"Spatial Coverage","isShared":true,"idf":2.78,"freqPct":6.2},{"source":"item_9534","target":"resource_2243","name":"Subject","isShared":true,"idf":2.79,"freqPct":6.2},{"source":"item_9534","target":"resource_2024","name":"Subject","isShared":true,"idf":2.79,"freqPct":6.2},{"source":"item_9534","target":"resource_2237","name":"Subject","isShared":true,"idf":2.78,"freqPct":6.2},{"source":"item_9534","target":"resource_2057","name":"Subject","isShared":true,"idf":2.37,"freqPct":9.3},{"source":"item_9534","target":"resource_2234","name":"Subject","isShared":true,"idf":3.86,"freqPct":2.1},{"source":"item_9534","target":"resource_2752","name":"Subject","isShared":true,"idf":3.0,"freqPct":5.0},{"source":"item_9534","target":"resource_2657","name":"Subject","isShared":true,"idf":2.78,"freqPct":6.2},{"source":"item_9534","target":"resource_2825","name":"Subject","isShared":true,"idf":2.71,"freqPct":6.6},{"source":"item_9534","target":"resource_215","name":"collector","isShared":true,"idf":2.79,"freqPct":6.2},{"source":"item_9534","target":"resource_1796","name":"Is Part Of","isShared":true,"idf":2.5,"freqPct":8.2},{"source":"item_9534","target":"resource_1956","name":"Spatial Coverage","isShared":true,"idf":2.78,"freqPct":6.2},{"source":"item_9535","target":"resource_2243","name":"Subject","isShared":true,"idf":2.79,"freqPct":6.2},{"source":"item_9535","target":"resource_2024","name":"Subject","isShared":true,"idf":2.79,"freqPct":6.2},{"source":"item_9535","target":"resource_2237","name":"Subject","isShared":true,"idf":2.78,"freqPct":6.2},{"source":"item_9535","target":"resource_2057","name":"Subject","isShared":true,"idf":2.37,"freqPct":9.3},{"source":"item_9535","target":"resource_2234","name":"Subject","isShared":true,"idf":3.86,"freqPct":2.1},{"source":"item_9535","target":"resource_2752","name":"Subject","isShared":true,"idf":3.0,"freqPct":5.0},{"source":"item_9535","target":"resource_2657","name":"Subject","isShared":true,"idf":2.78,"freqPct":6.2},{"source":"item_9535","target":"resource_2825","name":"Subject","isShared":true,"idf":2.71,"freqPct":6.6},{"source":"item_9535","target":"resource_215","name":"collector","isShared":true,"idf":2.79,"freqPct":6.2},{"source":"item_9535","target":"resource_1796","name":"Is Part Of","isShared":true,"idf":2.5,"freqPct":8.2},{"source":"item_9535","target":"resource_1956","name":"Spatial Coverage","isShared":true,"idf":2.78,"freqPct":6.2},{"source":"item_9536","target":"resource_2243","name":"Subject","isShared":true,"idf":2.79,"freqPct":6.2},{"source":"item_9536","target":"resource_2024","name":"Subject","isShared":true,"idf":2.79,"freqPct":6.2},{"source":"item_9536","target":"resource_2237","name":"Subject","isShared":true,"idf":2.78,"freqPct":6.2},{"source":"item_9536","target":"resource_2057","name":"Subject","isShared":true,"idf":2.37,"freqPct":9.3},{"source":"item_9536","target":"resource_2234","name":"Subject","isShared":true,"idf":3.86,"freqPct":2.1},{"source":"item_9536","target":"resource_2752","name":"Subject","isShared":true,"idf":3.0,"freqPct":5.0},{"source":"item_9536","target":"resource_2657","name":"Subject","isShared":true,"idf":2.78,"freqPct":6.2},{"source":"item_9536","target":"resource_2825","name":"Subject","isShared":true,"idf":2.71,"freqPct":6.6},{"source":"item_9536","target":"resource_215","name":"collector","isShared":true,"idf":2.79,"freqPct":6.2},{"source":"item_9536","target":"resource_1796","name":"Is Part Of","isShared":true,"idf":2.5,"freqPct":8.2},{"source":"item_9536","target":"resource_1956","name":"Spatial Coverage","isShared":true,"idf":2.78,"freqPct":6.2},{"source":"item_9555","target":"resource_2243","name":"Subject","isShared":true,"idf":2.79,"freqPct":6.2},{"source":"item_9555","target":"resource_2024","name":"Subject","isShared":true,"idf":2.79,"freqPct":6.2},{"source":"item_9555","target":"resource_2237","name":"Subject","isShared":true,"idf":2.78,"freqPct":6.2},{"source":"item_9555","target":"resource_2057","name":"Subject","isShared":true,"idf":2.37,"freqPct":9.3},{"source":"item_9555","target":"resource_2234","name":"Subject","isShared":true,"idf":3.86,"freqPct":2.1},{"source":"item_9555","target":"resource_2752","name":"Subject","isShared":true,"idf":3.0,"freqPct":5.0},{"source":"item_9555","target":"resource_2657","name":"Subject","isShared":true,"idf":2.78,"freqPct":6.2},{"source":"item_9555","target":"resource_2825","name":"Subject","isShared":true,"idf":2.71,"freqPct":6.6},{"source":"item_9555","target":"resource_215","name":"collector","isShared":true,"idf":2.79,"freqPct":6.2},{"source":"item_9555","target":"resource_1796","name":"Is Part Of","isShared":true,"idf":2.5,"freqPct":8.2},{"source":"item_9555","target":"resource_1956","name":"Spatial Coverage","isShared":true,"idf":2.78,"freqPct":6.2},{"source":"item_9556","target":"resource_2243","name":"Subject","isShared":true,"idf":2.79,"freqPct":6.2},{"source":"item_9556","target":"resource_2024","name":"Subject","isShared":true,"idf":2.79,"freqPct":6.2},{"source":"item_9556","target":"resource_2237","name":"Subject","isShared":true,"idf":2.78,"freqPct":6.2},{"source":"item_9556","target":"resource_2057","name":"Subject","isShared":true,"idf":2.37,"freqPct":9.3},{"source":"item_9556","target":"resource_2234","name":"Subject","isShared":true,"idf":3.86,"freqPct":2.1},{"source":"item_9556","target":"resource_2752","name":"Subject","isShared":true,"idf":3.0,"freqPct":5.0},{"source":"item_9556","target":"resource_2657","name":"Subject","isShared":true,"idf":2.78,"freqPct":6.2},{"source":"item_9556","target":"resource_2825","name":"Subject","isShared":true,"idf":2.71,"freqPct":6.6},{"source":"item_9556","target":"resource_215","name":"collector","isShared":true,"idf":2.79,"freqPct":6.2},{"source":"item_9556","target":"resource_1796","name":"Is Part Of","isShared":true,"idf":2.5,"freqPct":8.2},{"source":"item_9556","target":"resource_1956","name":"Spatial Coverage","isShared":true,"idf":2.78,"freqPct":6.2},{"source":"item_9557","target":"resource_2243","name":"Subject","isShared":true,"idf":2.79,"freqPct":6.2},{"source":"item_9557","target":"resource_2024","name":"Subject","isShared":true,"idf":2.79,"freqPct":6.2},{"source":"item_9557","target":"resource_2237","name":"Subject","isShared":true,"idf":2.78,"freqPct":6.2},{"source":"item_9557","target":"resource_2057","name":"Subject","isShared":true,"idf":2.37,"freqPct":9.3},{"source":"item_9557","target":"resource_2234","name":"Subject","isShared":true,"idf":3.86,"freqPct":2.1},{"source":"item_9557","target":"resource_2752","name":"Subject","isShared":true,"idf":3.0,"freqPct":5.0},{"source":"item_9557","target":"resource_2657","name":"Subject","isShared":true,"idf":2.78,"freqPct":6.2},{"source":"item_9557","target":"resource_2825","name":"Subject","isShared":true,"idf":2.71,"freqPct":6.6},{"source":"item_9557","target":"resource_215","name":"collector","isShared":true,"idf":2.79,"freqPct":6.2},{"source":"item_9557","target":"resource_1796","name":"Is Part Of","isShared":true,"idf":2.5,"freqPct":8.2},{"source":"item_9557","target":"resource_1956","name":"Spatial Coverage","isShared":true,"idf":2.78,"freqPct":6.2},{"source":"item_9558","target":"resource_2243","name":"Subject","isShared":true,"idf":2.79,"freqPct":6.2},{"source":"item_9558","target":"resource_2024","name":"Subject","isShared":true,"idf":2.79,"freqPct":6.2},{"source":"item_9558","target":"resource_2237","name":"Subject","isShared":true,"idf":2.78,"freqPct":6.2},{"source":"item_9558","target":"resource_2057","name":"Subject","isShared":true,"idf":2.37,"freqPct":9.3},{"source":"item_9558","target":"resource_2234","name":"Subject","isShared":true,"idf":3.86,"freqPct":2.1},{"source":"item_9558","target":"resource_2752","name":"Subject","isShared":true,"idf":3.0,"freqPct":5.0},{"source":"item_9558","target":"resource_2657","name":"Subject","isShared":true,"idf":2.78,"freqPct":6.2},{"source":"item_9558","target":"resource_2825","name":"Subject","isShared":true,"idf":2.71,"freqPct":6.6},{"source":"item_9558","target":"resource_215","name":"collector","isShared":true,"idf":2.79,"freqPct":6.2},{"source":"item_9558","target":"resource_1796","name":"Is Part Of","isShared":true,"idf":2.5,"freqPct":8.2},{"source":"item_9558","target":"resource_1956","name":"Spatial Coverage","isShared":true,"idf":2.78,"freqPct":6.2},{"source":"item_9559","target":"resource_2243","name":"Subject","isShared":true,"idf":2.79,"freqPct":6.2},{"source":"item_9559","target":"resource_2024","name":"Subject","isShared":true,"idf":2.79,"freqPct":6.2},{"source":"item_9559","target":"resource_2237","name":"Subject","isShared":true,"idf":2.78,"freqPct":6.2},{"source":"item_9559","target":"resource_2057","name":"Subject","isShared":true,"idf":2.37,"freqPct":9.3},{"source":"item_9559","target":"resource_2234","name":"Subject","isShared":true,"idf":3.86,"freqPct":2.1},{"source":"item_9559","target":"resource_2752","name":"Subject","isShared":true,"idf":3.0,"freqPct":5.0},{"source":"item_9559","target":"resource_2657","name":"Subject","isShared":true,"idf":2.78,"freqPct":6.2},{"source":"item_9559","target":"resource_2825","name":"Subject","isShared":true,"idf":2.71,"freqPct":6.6},{"source":"item_9559","target":"resource_215","name":"collector","isShared":true,"idf":2.79,"freqPct":6.2},{"source":"item_9559","target":"resource_1796","name":"Is Part Of","isShared":true,"idf":2.5,"freqPct":8.2},{"source":"item_9559","target":"resource_1956","name":"Spatial Coverage","isShared":true,"idf":2.78,"freqPct":6.2},{"source":"item_9560","target":"resource_2243","name":"Subject","isShared":true,"idf":2.79,"freqPct":6.2},{"source":"item_9560","target":"resource_2024","name":"Subject","isShared":true,"idf":2.79,"freqPct":6.2},{"source":"item_9560","target":"resource_2237","name":"Subject","isShared":true,"idf":2.78,"freqPct":6.2},{"source":"item_9560","target":"resource_2057","name":"Subject","isShared":true,"idf":2.37,"freqPct":9.3},{"source":"item_9560","target":"resource_2234","name":"Subject","isShared":true,"idf":3.86,"freqPct":2.1},{"source":"item_9560","target":"resource_2752","name":"Subject","isShared":true,"idf":3.0,"freqPct":5.0},{"source":"item_9560","target":"resource_2657","name":"Subject","isShared":true,"idf":2.78,"freqPct":6.2},{"source":"item_9560","target":"resource_2825","name":"Subject","isShared":true,"idf":2.71,"freqPct":6.6},{"source":"item_9560","target":"resource_215","name":"collector","isShared":true,"idf":2.79,"freqPct":6.2},{"source":"item_9560","target":"resource_1796","name":"Is Part Of","isShared":true,"idf":2.5,"freqPct":8.2},{"source":"item_9560","target":"resource_1956","name":"Spatial Coverage","isShared":true,"idf":2.78,"freqPct":6.2},{"source":"item_9561","target":"resource_2243","name":"Subject","isShared":true,"idf":2.79,"freqPct":6.2},{"source":"item_9561","target":"resource_2024","name":"Subject","isShared":true,"idf":2.79,"freqPct":6.2},{"source":"item_9561","target":"resource_2237","name":"Subject","isShared":true,"idf":2.78,"freqPct":6.2},{"source":"item_9561","target":"resource_2057","name":"Subject","isShared":true,"idf":2.37,"freqPct":9.3},{"source":"item_9561","target":"resource_2234","name":"Subject","isShared":true,"idf":3.86,"freqPct":2.1},{"source":"item_9561","target":"resource_2752","name":"Subject","isShared":true,"idf":3.0,"freqPct":5.0},{"source":"item_9561","target":"resource_2657","name":"Subject","isShared":true,"idf":2.78,"freqPct":6.2},{"source":"item_9561","target":"resource_2825","name":"Subject","isShared":true,"idf":2.71,"freqPct":6.6},{"source":"item_9561","target":"resource_215","name":"collector","isShared":true,"idf":2.79,"freqPct":6.2},{"source":"item_9561","target":"resource_1796","name":"Is Part Of","isShared":true,"idf":2.5,"freqPct":8.2},{"source":"item_9561","target":"resource_1956","name":"Spatial Coverage","isShared":true,"idf":2.78,"freqPct":6.2},{"source":"item_9562","target":"resource_2243","name":"Subject","isShared":true,"idf":2.79,"freqPct":6.2},{"source":"item_9562","target":"resource_2024","name":"Subject","isShared":true,"idf":2.79,"freqPct":6.2},{"source":"item_9562","target":"resource_2237","name":"Subject","isShared":true,"idf":2.78,"freqPct":6.2},{"source":"item_9562","target":"resource_2057","name":"Subject","isShared":true,"idf":2.37,"freqPct":9.3},{"source":"item_9562","target":"resource_2234","name":"Subject","isShared":true,"idf":3.86,"freqPct":2.1},{"source":"item_9562","target":"resource_2752","name":"Subject","isShared":true,"idf":3.0,"freqPct":5.0},{"source":"item_9562","target":"resource_2657","name":"Subject","isShared":true,"idf":2.78,"freqPct":6.2},{"source":"item_9562","target":"resource_2825","name":"Subject","isShared":true,"idf":2.71,"freqPct":6.6},{"source":"item_9562","target":"resource_215","name":"collector","isShared":true,"idf":2.79,"freqPct":6.2},{"source":"item_9562","target":"resource_1796","name":"Is Part Of","isShared":true,"idf":2.5,"freqPct":8.2},{"source":"item_9562","target":"resource_1956","name":"Spatial Coverage","isShared":true,"idf":2.78,"freqPct":6.2},{"source":"item_9563","target":"resource_2243","name":"Subject","isShared":true,"idf":2.79,"freqPct":6.2},{"source":"item_9563","target":"resource_2024","name":"Subject","isShared":true,"idf":2.79,"freqPct":6.2},{"source":"item_9563","target":"resource_2237","name":"Subject","isShared":true,"idf":2.78,"freqPct":6.2},{"source":"item_9563","target":"resource_2057","name":"Subject","isShared":true,"idf":2.37,"freqPct":9.3},{"source":"item_9563","target":"resource_2234","name":"Subject","isShared":true,"idf":3.86,"freqPct":2.1},{"source":"item_9563","target":"resource_2752","name":"Subject","isShared":true,"idf":3.0,"freqPct":5.0},{"source":"item_9563","target":"resource_2657","name":"Subject","isShared":true,"idf":2.78,"freqPct":6.2},{"source":"item_9563","target":"resource_2825","name":"Subject","isShared":true,"idf":2.71,"freqPct":6.6},{"source":"item_9563","target":"resource_215","name":"collector","isShared":true,"idf":2.79,"freqPct":6.2},{"source":"item_9563","target":"resource_1796","name":"Is Part Of","isShared":true,"idf":2.5,"freqPct":8.2},{"source":"item_9563","target":"resource_1956","name":"Spatial Coverage","isShared":true,"idf":2.78,"freqPct":6.2},{"source":"item_9564","target":"resource_2243","name":"Subject","isShared":true,"idf":2.79,"freqPct":6.2},{"source":"item_9564","target":"resource_2024","name":"Subject","isShared":true,"idf":2.79,"freqPct":6.2},{"source":"item_9564","target":"resource_2237","name":"Subject","isShared":true,"idf":2.78,"freqPct":6.2},{"source":"item_9564","target":"resource_2057","name":"Subject","isShared":true,"idf":2.37,"freqPct":9.3},{"source":"item_9564","target":"resource_2234","name":"Subject","isShared":true,"idf":3.86,"freqPct":2.1},{"source":"item_9564","target":"resource_2752","name":"Subject","isShared":true,"idf":3.0,"freqPct":5.0},{"source":"item_9564","target":"resource_2657","name":"Subject","isShared":true,"idf":2.78,"freqPct":6.2},{"source":"item_9564","target":"resource_2825","name":"Subject","isShared":true,"idf":2.71,"freqPct":6.6},{"source":"item_9564","target":"resource_215","name":"collector","isShared":true,"idf":2.79,"freqPct":6.2},{"source":"item_9564","target":"resource_1796","name":"Is Part Of","isShared":true,"idf":2.5,"freqPct":8.2},{"source":"item_9564","target":"resource_1956","name":"Spatial Coverage","isShared":true,"idf":2.78,"freqPct":6.2},{"source":"item_9565","target":"resource_2243","name":"Subject","isShared":true,"idf":2.79,"freqPct":6.2},{"source":"item_9565","target":"resource_2024","name":"Subject","isShared":true,"idf":2.79,"freqPct":6.2},{"source":"item_9565","target":"resource_2237","name":"Subject","isShared":true,"idf":2.78,"freqPct":6.2},{"source":"item_9565","target":"resource_2057","name":"Subject","isShared":true,"idf":2.37,"freqPct":9.3},{"source":"item_9565","target":"resource_2234","name":"Subject","isShared":true,"idf":3.86,"freqPct":2.1},{"source":"item_9565","target":"resource_2752","name":"Subject","isShared":true,"idf":3.0,"freqPct":5.0},{"source":"item_9565","target":"resource_2657","name":"Subject","isShared":true,"idf":2.78,"freqPct":6.2},{"source":"item_9565","target":"resource_2825","name":"Subject","isShared":true,"idf":2.71,"freqPct":6.6},{"source":"item_9565","target":"resource_215","name":"collector","isShared":true,"idf":2.79,"freqPct":6.2},{"source":"item_9565","target":"resource_1796","name":"Is Part Of","isShared":true,"idf":2.5,"freqPct":8.2},{"source":"item_9565","target":"resource_1956","name":"Spatial Coverage","isShared":true,"idf":2.78,"freqPct":6.2},{"source":"item_9566","target":"resource_2243","name":"Subject","isShared":true,"idf":2.79,"freqPct":6.2},{"source":"item_9566","target":"resource_2024","name":"Subject","isShared":true,"idf":2.79,"freqPct":6.2},{"source":"item_9566","target":"resource_2237","name":"Subject","isShared":true,"idf":2.78,"freqPct":6.2},{"source":"item_9566","target":"resource_2057","name":"Subject","isShared":true,"idf":2.37,"freqPct":9.3},{"source":"item_9566","target":"resource_2234","name":"Subject","isShared":true,"idf":3.86,"freqPct":2.1},{"source":"item_9566","target":"resource_2752","name":"Subject","isShared":true,"idf":3.0,"freqPct":5.0},{"source":"item_9566","target":"resource_2657","name":"Subject","isShared":true,"idf":2.78,"freqPct":6.2},{"source":"item_9566","target":"resource_2825","name":"Subject","isShared":true,"idf":2.71,"freqPct":6.6},{"source":"item_9566","target":"resource_215","name":"collector","isShared":true,"idf":2.79,"freqPct":6.2},{"source":"item_9566","target":"resource_1796","name":"Is Part Of","isShared":true,"idf":2.5,"freqPct":8.2},{"source":"item_9566","target":"resource_1956","name":"Spatial Coverage","isShared":true,"idf":2.78,"freqPct":6.2},{"source":"item_9568","target":"resource_2243","name":"Subject","isShared":true,"idf":2.79,"freqPct":6.2},{"source":"item_9568","target":"resource_2024","name":"Subject","isShared":true,"idf":2.79,"freqPct":6.2},{"source":"item_9568","target":"resource_2237","name":"Subject","isShared":true,"idf":2.78,"freqPct":6.2},{"source":"item_9568","target":"resource_2057","name":"Subject","isShared":true,"idf":2.37,"freqPct":9.3},{"source":"item_9568","target":"resource_2234","name":"Subject","isShared":true,"idf":3.86,"freqPct":2.1},{"source":"item_9568","target":"resource_2752","name":"Subject","isShared":true,"idf":3.0,"freqPct":5.0},{"source":"item_9568","target":"resource_2657","name":"Subject","isShared":true,"idf":2.78,"freqPct":6.2},{"source":"item_9568","target":"resource_2825","name":"Subject","isShared":true,"idf":2.71,"freqPct":6.6},{"source":"item_9568","target":"resource_215","name":"collector","isShared":true,"idf":2.79,"freqPct":6.2},{"source":"item_9568","target":"resource_1796","name":"Is Part Of","isShared":true,"idf":2.5,"freqPct":8.2},{"source":"item_9568","target":"resource_1956","name":"Spatial Coverage","isShared":true,"idf":2.78,"freqPct":6.2},{"source":"item_9569","target":"resource_2243","name":"Subject","isShared":true,"idf":2.79,"freqPct":6.2},{"source":"item_9569","target":"resource_2024","name":"Subject","isShared":true,"idf":2.79,"freqPct":6.2},{"source":"item_9569","target":"resource_2237","name":"Subject","isShared":true,"idf":2.78,"freqPct":6.2},{"source":"item_9569","target":"resource_2057","name":"Subject","isShared":true,"idf":2.37,"freqPct":9.3},{"source":"item_9569","target":"resource_2234","name":"Subject","isShared":true,"idf":3.86,"freqPct":2.1},{"source":"item_9569","target":"resource_2752","name":"Subject","isShared":true,"idf":3.0,"freqPct":5.0},{"source":"item_9569","target":"resource_2657","name":"Subject","isShared":true,"idf":2.78,"freqPct":6.2},{"source":"item_9569","target":"resource_2825","name":"Subject","isShared":true,"idf":2.71,"freqPct":6.6},{"source":"item_9569","target":"resource_215","name":"collector","isShared":true,"idf":2.79,"freqPct":6.2},{"source":"item_9569","target":"resource_1796","name":"Is Part Of","isShared":true,"idf":2.5,"freqPct":8.2},{"source":"item_9569","target":"resource_1956","name":"Spatial Coverage","isShared":true,"idf":2.78,"freqPct":6.2},{"source":"item_9570","target":"resource_2243","name":"Subject","isShared":true,"idf":2.79,"freqPct":6.2},{"source":"item_9570","target":"resource_2024","name":"Subject","isShared":true,"idf":2.79,"freqPct":6.2},{"source":"item_9570","target":"resource_2237","name":"Subject","isShared":true,"idf":2.78,"freqPct":6.2},{"source":"item_9570","target":"resource_2057","name":"Subject","isShared":true,"idf":2.37,"freqPct":9.3},{"source":"item_9570","target":"resource_2234","name":"Subject","isShared":true,"idf":3.86,"freqPct":2.1},{"source":"item_9570","target":"resource_2752","name":"Subject","isShared":true,"idf":3.0,"freqPct":5.0},{"source":"item_9570","target":"resource_2657","name":"Subject","isShared":true,"idf":2.78,"freqPct":6.2},{"source":"item_9570","target":"resource_2825","name":"Subject","isShared":true,"idf":2.71,"freqPct":6.6},{"source":"item_9570","target":"resource_215","name":"collector","isShared":true,"idf":2.79,"freqPct":6.2},{"source":"item_9570","target":"resource_1796","name":"Is Part Of","isShared":true,"idf":2.5,"freqPct":8.2},{"source":"item_9570","target":"resource_1956","name":"Spatial Coverage","isShared":true,"idf":2.78,"freqPct":6.2},{"source":"item_9379","target":"resource_2243","name":"Subject","isShared":true,"idf":2.79,"freqPct":6.2},{"source":"item_9379","target":"resource_2024","name":"Subject","isShared":true,"idf":2.79,"freqPct":6.2},{"source":"item_9379","target":"resource_2237","name":"Subject","isShared":true,"idf":2.78,"freqPct":6.2},{"source":"item_9379","target":"resource_2057","name":"Subject","isShared":true,"idf":2.37,"freqPct":9.3},{"source":"item_9379","target":"resource_2752","name":"Subject","isShared":true,"idf":3.0,"freqPct":5.0},{"source":"item_9379","target":"resource_2657","name":"Subject","isShared":true,"idf":2.78,"freqPct":6.2},{"source":"item_9379","target":"resource_2825","name":"Subject","isShared":true,"idf":2.71,"freqPct":6.6},{"source":"item_9379","target":"resource_215","name":"collector","isShared":true,"idf":2.79,"freqPct":6.2},{"source":"item_9379","target":"resource_1796","name":"Is Part Of","isShared":true,"idf":2.5,"freqPct":8.2},{"source":"item_9379","target":"resource_1956","name":"Spatial Coverage","isShared":true,"idf":2.78,"freqPct":6.2},{"source":"item_9381","target":"resource_2243","name":"Subject","isShared":true,"idf":2.79,"freqPct":6.2},{"source":"item_9381","target":"resource_2024","name":"Subject","isShared":true,"idf":2.79,"freqPct":6.2},{"source":"item_9381","target":"resource_2237","name":"Subject","isShared":true,"idf":2.78,"freqPct":6.2},{"source":"item_9381","target":"resource_2057","name":"Subject","isShared":true,"idf":2.37,"freqPct":9.3},{"source":"item_9381","target":"resource_2752","name":"Subject","isShared":true,"idf":3.0,"freqPct":5.0},{"source":"item_9381","target":"resource_2657","name":"Subject","isShared":true,"idf":2.78,"freqPct":6.2},{"source":"item_9381","target":"resource_2825","name":"Subject","isShared":true,"idf":2.71,"freqPct":6.6},{"source":"item_9381","target":"resource_215","name":"collector","isShared":true,"idf":2.79,"freqPct":6.2},{"source":"item_9381","target":"resource_1796","name":"Is Part Of","isShared":true,"idf":2.5,"freqPct":8.2},{"source":"item_9381","target":"resource_1956","name":"Spatial Coverage","isShared":true,"idf":2.78,"freqPct":6.2},{"source":"item_9407","target":"resource_2243","name":"Subject","isShared":true,"idf":2.79,"freqPct":6.2},{"source":"item_9407","target":"resource_2024","name":"Subject","isShared":true,"idf":2.79,"freqPct":6.2},{"source":"item_9407","target":"resource_2237","name":"Subject","isShared":true,"idf":2.78,"freqPct":6.2},{"source":"item_9407","target":"resource_2057","name":"Subject","isShared":true,"idf":2.37,"freqPct":9.3},{"source":"item_9407","target":"resource_2752","name":"Subject","isShared":true,"idf":3.0,"freqPct":5.0},{"source":"item_9407","target":"resource_2657","name":"Subject","isShared":true,"idf":2.78,"freqPct":6.2},{"source":"item_9407","target":"resource_2825","name":"Subject","isShared":true,"idf":2.71,"freqPct":6.6},{"source":"item_9407","target":"resource_215","name":"collector","isShared":true,"idf":2.79,"freqPct":6.2},{"source":"item_9407","target":"resource_1796","name":"Is Part Of","isShared":true,"idf":2.5,"freqPct":8.2},{"source":"item_9407","target":"resource_1956","name":"Spatial Coverage","isShared":true,"idf":2.78,"freqPct":6.2},{"source":"item_9408","target":"resource_2243","name":"Subject","isShared":true,"idf":2.79,"freqPct":6.2},{"source":"item_9408","target":"resource_2024","name":"Subject","isShared":true,"idf":2.79,"freqPct":6.2},{"source":"item_9408","target":"resource_2237","name":"Subject","isShared":true,"idf":2.78,"freqPct":6.2},{"source":"item_9408","target":"resource_2057","name":"Subject","isShared":true,"idf":2.37,"freqPct":9.3},{"source":"item_9408","target":"resource_2752","name":"Subject","isShared":true,"idf":3.0,"freqPct":5.0},{"source":"item_9408","target":"resource_2657","name":"Subject","isShared":true,"idf":2.78,"freqPct":6.2},{"source":"item_9408","target":"resource_2825","name":"Subject","isShared":true,"idf":2.71,"freqPct":6.6},{"source":"item_9408","target":"resource_215","name":"collector","isShared":true,"idf":2.79,"freqPct":6.2},{"source":"item_9408","target":"resource_1796","name":"Is Part Of","isShared":true,"idf":2.5,"freqPct":8.2},{"source":"item_9408","target":"resource_1956","name":"Spatial Coverage","isShared":true,"idf":2.78,"freqPct":6.2},{"source":"item_9409","target":"resource_2243","name":"Subject","isShared":true,"idf":2.79,"freqPct":6.2},{"source":"item_9409","target":"resource_2024","name":"Subject","isShared":true,"idf":2.79,"freqPct":6.2},{"source":"item_9409","target":"resource_2237","name":"Subject","isShared":true,"idf":2.78,"freqPct":6.2},{"source":"item_9409","target":"resource_2057","name":"Subject","isShared":true,"idf":2.37,"freqPct":9.3},{"source":"item_9409","target":"resource_2752","name":"Subject","isShared":true,"idf":3.0,"freqPct":5.0},{"source":"item_9409","target":"resource_2657","name":"Subject","isShared":true,"idf":2.78,"freqPct":6.2},{"source":"item_9409","target":"resource_2825","name":"Subject","isShared":true,"idf":2.71,"freqPct":6.6},{"source":"item_9409","target":"resource_215","name":"collector","isShared":true,"idf":2.79,"freqPct":6.2},{"source":"item_9409","target":"resource_1796","name":"Is Part Of","isShared":true,"idf":2.5,"freqPct":8.2},{"source":"item_9409","target":"resource_1956","name":"Spatial Coverage","isShared":true,"idf":2.78,"freqPct":6.2},{"source":"item_9410","target":"resource_2243","name":"Subject","isShared":true,"idf":2.79,"freqPct":6.2},{"source":"item_9410","target":"resource_2024","name":"Subject","isShared":true,"idf":2.79,"freqPct":6.2},{"source":"item_9410","target":"resource_2237","name":"Subject","isShared":true,"idf":2.78,"freqPct":6.2},{"source":"item_9410","target":"resource_2057","name":"Subject","isShared":true,"idf":2.37,"freqPct":9.3},{"source":"item_9410","target":"resource_2752","name":"Subject","isShared":true,"idf":3.0,"freqPct":5.0},{"source":"item_9410","target":"resource_2657","name":"Subject","isShared":true,"idf":2.78,"freqPct":6.2},{"source":"item_9410","target":"resource_2825","name":"Subject","isShared":true,"idf":2.71,"freqPct":6.6},{"source":"item_9410","target":"resource_215","name":"collector","isShared":true,"idf":2.79,"freqPct":6.2},{"source":"item_9410","target":"resource_1796","name":"Is Part Of","isShared":true,"idf":2.5,"freqPct":8.2},{"source":"item_9410","target":"resource_1956","name":"Spatial Coverage","isShared":true,"idf":2.78,"freqPct":6.2},{"source":"item_9411","target":"resource_2243","name":"Subject","isShared":true,"idf":2.79,"freqPct":6.2},{"source":"item_9411","target":"resource_2024","name":"Subject","isShared":true,"idf":2.79,"freqPct":6.2},{"source":"item_9411","target":"resource_2237","name":"Subject","isShared":true,"idf":2.78,"freqPct":6.2},{"source":"item_9411","target":"resource_2057","name":"Subject","isShared":true,"idf":2.37,"freqPct":9.3},{"source":"item_9411","target":"resource_2752","name":"Subject","isShared":true,"idf":3.0,"freqPct":5.0},{"source":"item_9411","target":"resource_2657","name":"Subject","isShared":true,"idf":2.78,"freqPct":6.2},{"source":"item_9411","target":"resource_2825","name":"Subject","isShared":true,"idf":2.71,"freqPct":6.6},{"source":"item_9411","target":"resource_215","name":"collector","isShared":true,"idf":2.79,"freqPct":6.2},{"source":"item_9411","target":"resource_1796","name":"Is Part Of","isShared":true,"idf":2.5,"freqPct":8.2},{"source":"item_9411","target":"resource_1956","name":"Spatial Coverage","isShared":true,"idf":2.78,"freqPct":6.2},{"source":"item_9412","target":"resource_2243","name":"Subject","isShared":true,"idf":2.79,"freqPct":6.2},{"source":"item_9412","target":"resource_2024","name":"Subject","isShared":true,"idf":2.79,"freqPct":6.2},{"source":"item_9412","target":"resource_2237","name":"Subject","isShared":true,"idf":2.78,"freqPct":6.2},{"source":"item_9412","target":"resource_2057","name":"Subject","isShared":true,"idf":2.37,"freqPct":9.3},{"source":"item_9412","target":"resource_2752","name":"Subject","isShared":true,"idf":3.0,"freqPct":5.0},{"source":"item_9412","target":"resource_2657","name":"Subject","isShared":true,"idf":2.78,"freqPct":6.2},{"source":"item_9412","target":"resource_2825","name":"Subject","isShared":true,"idf":2.71,"freqPct":6.6},{"source":"item_9412","target":"resource_215","name":"collector","isShared":true,"idf":2.79,"freqPct":6.2},{"source":"item_9412","target":"resource_1796","name":"Is Part Of","isShared":true,"idf":2.5,"freqPct":8.2},{"source":"item_9412","target":"resource_1956","name":"Spatial Coverage","isShared":true,"idf":2.78,"freqPct":6.2},{"source":"item_9413","target":"resource_2243","name":"Subject","isShared":true,"idf":2.79,"freqPct":6.2},{"source":"item_9413","target":"resource_2024","name":"Subject","isShared":true,"idf":2.79,"freqPct":6.2},{"source":"item_9413","target":"resource_2237","name":"Subject","isShared":true,"idf":2.78,"freqPct":6.2},{"source":"item_9413","target":"resource_2057","name":"Subject","isShared":true,"idf":2.37,"freqPct":9.3},{"source":"item_9413","target":"resource_2752","name":"Subject","isShared":true,"idf":3.0,"freqPct":5.0},{"source":"item_9413","target":"resource_2657","name":"Subject","isShared":true,"idf":2.78,"freqPct":6.2},{"source":"item_9413","target":"resource_2825","name":"Subject","isShared":true,"idf":2.71,"freqPct":6.6},{"source":"item_9413","target":"resource_215","name":"collector","isShared":true,"idf":2.79,"freqPct":6.2},{"source":"item_9413","target":"resource_1796","name":"Is Part Of","isShared":true,"idf":2.5,"freqPct":8.2},{"source":"item_9413","target":"resource_1956","name":"Spatial Coverage","isShared":true,"idf":2.78,"freqPct":6.2},{"source":"item_9414","target":"resource_2243","name":"Subject","isShared":true,"idf":2.79,"freqPct":6.2},{"source":"item_9414","target":"resource_2024","name":"Subject","isShared":true,"idf":2.79,"freqPct":6.2},{"source":"item_9414","target":"resource_2237","name":"Subject","isShared":true,"idf":2.78,"freqPct":6.2},{"source":"item_9414","target":"resource_2057","name":"Subject","isShared":true,"idf":2.37,"freqPct":9.3},{"source":"item_9414","target":"resource_2752","name":"Subject","isShared":true,"idf":3.0,"freqPct":5.0},{"source":"item_9414","target":"resource_2657","name":"Subject","isShared":true,"idf":2.78,"freqPct":6.2},{"source":"item_9414","target":"resource_2825","name":"Subject","isShared":true,"idf":2.71,"freqPct":6.6},{"source":"item_9414","target":"resource_215","name":"collector","isShared":true,"idf":2.79,"freqPct":6.2},{"source":"item_9414","target":"resource_1796","name":"Is Part Of","isShared":true,"idf":2.5,"freqPct":8.2},{"source":"item_9414","target":"resource_1956","name":"Spatial Coverage","isShared":true,"idf":2.78,"freqPct":6.2},{"source":"item_9415","target":"resource_2243","name":"Subject","isShared":true,"idf":2.79,"freqPct":6.2},{"source":"item_9415","target":"resource_2024","name":"Subject","isShared":true,"idf":2.79,"freqPct":6.2},{"source":"item_9415","target":"resource_2237","name":"Subject","isShared":true,"idf":2.78,"freqPct":6.2},{"source":"item_9415","target":"resource_2057","name":"Subject","isShared":true,"idf":2.37,"freqPct":9.3},{"source":"item_9415","target":"resource_2752","name":"Subject","isShared":true,"idf":3.0,"freqPct":5.0},{"source":"item_9415","target":"resource_2657","name":"Subject","isShared":true,"idf":2.78,"freqPct":6.2},{"source":"item_9415","target":"resource_2825","name":"Subject","isShared":true,"idf":2.71,"freqPct":6.6},{"source":"item_9415","target":"resource_215","name":"collector","isShared":true,"idf":2.79,"freqPct":6.2},{"source":"item_9415","target":"resource_1796","name":"Is Part Of","isShared":true,"idf":2.5,"freqPct":8.2},{"source":"item_9415","target":"resource_1956","name":"Spatial Coverage","isShared":true,"idf":2.78,"freqPct":6.2},{"source":"item_9416","target":"resource_2243","name":"Subject","isShared":true,"idf":2.79,"freqPct":6.2},{"source":"item_9416","target":"resource_2024","name":"Subject","isShared":true,"idf":2.79,"freqPct":6.2},{"source":"item_9416","target":"resource_2237","name":"Subject","isShared":true,"idf":2.78,"freqPct":6.2},{"source":"item_9416","target":"resource_2057","name":"Subject","isShared":true,"idf":2.37,"freqPct":9.3},{"source":"item_9416","target":"resource_2752","name":"Subject","isShared":true,"idf":3.0,"freqPct":5.0},{"source":"item_9416","target":"resource_2657","name":"Subject","isShared":true,"idf":2.78,"freqPct":6.2},{"source":"item_9416","target":"resource_2825","name":"Subject","isShared":true,"idf":2.71,"freqPct":6.6},{"source":"item_9416","target":"resource_215","name":"collector","isShared":true,"idf":2.79,"freqPct":6.2},{"source":"item_9416","target":"resource_1796","name":"Is Part Of","isShared":true,"idf":2.5,"freqPct":8.2},{"source":"item_9416","target":"resource_1956","name":"Spatial Coverage","isShared":true,"idf":2.78,"freqPct":6.2},{"source":"item_9417","target":"resource_2243","name":"Subject","isShared":true,"idf":2.79,"freqPct":6.2},{"source":"item_9417","target":"resource_2024","name":"Subject","isShared":true,"idf":2.79,"freqPct":6.2},{"source":"item_9417","target":"resource_2237","name":"Subject","isShared":true,"idf":2.78,"freqPct":6.2},{"source":"item_9417","target":"resource_2057","name":"Subject","isShared":true,"idf":2.37,"freqPct":9.3},{"source":"item_9417","target":"resource_2752","name":"Subject","isShared":true,"idf":3.0,"freqPct":5.0},{"source":"item_9417","target":"resource_2657","name":"Subject","isShared":true,"idf":2.78,"freqPct":6.2},{"source":"item_9417","target":"resource_2825","name":"Subject","isShared":true,"idf":2.71,"freqPct":6.6},{"source":"item_9417","target":"resource_215","name":"collector","isShared":true,"idf":2.79,"freqPct":6.2},{"source":"item_9417","target":"resource_1796","name":"Is Part Of","isShared":true,"idf":2.5,"freqPct":8.2},{"source":"item_9417","target":"resource_1956","name":"Spatial Coverage","isShared":true,"idf":2.78,"freqPct":6.2},{"source":"item_9418","target":"resource_2243","name":"Subject","isShared":true,"idf":2.79,"freqPct":6.2},{"source":"item_9418","target":"resource_2024","name":"Subject","isShared":true,"idf":2.79,"freqPct":6.2},{"source":"item_9418","target":"resource_2237","name":"Subject","isShared":true,"idf":2.78,"freqPct":6.2},{"source":"item_9418","target":"resource_2057","name":"Subject","isShared":true,"idf":2.37,"freqPct":9.3},{"source":"item_9418","target":"resource_2752","name":"Subject","isShared":true,"idf":3.0,"freqPct":5.0},{"source":"item_9418","target":"resource_2657","name":"Subject","isShared":true,"idf":2.78,"freqPct":6.2},{"source":"item_9418","target":"resource_2825","name":"Subject","isShared":true,"idf":2.71,"freqPct":6.6},{"source":"item_9418","target":"resource_215","name":"collector","isShared":true,"idf":2.79,"freqPct":6.2},{"source":"item_9418","target":"resource_1796","name":"Is Part Of","isShared":true,"idf":2.5,"freqPct":8.2},{"source":"item_9418","target":"resource_1956","name":"Spatial Coverage","isShared":true,"idf":2.78,"freqPct":6.2},{"source":"item_9419","target":"resource_2243","name":"Subject","isShared":true,"idf":2.79,"freqPct":6.2},{"source":"item_9419","target":"resource_2024","name":"Subject","isShared":true,"idf":2.79,"freqPct":6.2},{"source":"item_9419","target":"resource_2237","name":"Subject","isShared":true,"idf":2.78,"freqPct":6.2},{"source":"item_9419","target":"resource_2057","name":"Subject","isShared":true,"idf":2.37,"freqPct":9.3},{"source":"item_9419","target":"resource_2752","name":"Subject","isShared":true,"idf":3.0,"freqPct":5.0},{"source":"item_9419","target":"resource_2657","name":"Subject","isShared":true,"idf":2.78,"freqPct":6.2},{"source":"item_9419","target":"resource_2825","name":"Subject","isShared":true,"idf":2.71,"freqPct":6.6},{"source":"item_9419","target":"resource_215","name":"collector","isShared":true,"idf":2.79,"freqPct":6.2},{"source":"item_9419","target":"resource_1796","name":"Is Part Of","isShared":true,"idf":2.5,"freqPct":8.2},{"source":"item_9419","target":"resource_1956","name":"Spatial Coverage","isShared":true,"idf":2.78,"freqPct":6.2},{"source":"item_9420","target":"resource_2243","name":"Subject","isShared":true,"idf":2.79,"freqPct":6.2},{"source":"item_9420","target":"resource_2024","name":"Subject","isShared":true,"idf":2.79,"freqPct":6.2},{"source":"item_9420","target":"resource_2237","name":"Subject","isShared":true,"idf":2.78,"freqPct":6.2},{"source":"item_9420","target":"resource_2057","name":"Subject","isShared":true,"idf":2.37,"freqPct":9.3},{"source":"item_9420","target":"resource_2752","name":"Subject","isShared":true,"idf":3.0,"freqPct":5.0},{"source":"item_9420","target":"resource_2657","name":"Subject","isShared":true,"idf":2.78,"freqPct":6.2},{"source":"item_9420","target":"resource_2825","name":"Subject","isShared":true,"idf":2.71,"freqPct":6.6},{"source":"item_9420","target":"resource_215","name":"collector","isShared":true,"idf":2.79,"freqPct":6.2},{"source":"item_9420","target":"resource_1796","name":"Is Part Of","isShared":true,"idf":2.5,"freqPct":8.2},{"source":"item_9420","target":"resource_1956","name":"Spatial Coverage","isShared":true,"idf":2.78,"freqPct":6.2},{"source":"item_9421","target":"resource_2243","name":"Subject","isShared":true,"idf":2.79,"freqPct":6.2},{"source":"item_9421","target":"resource_2024","name":"Subject","isShared":true,"idf":2.79,"freqPct":6.2},{"source":"item_9421","target":"resource_2237","name":"Subject","isShared":true,"idf":2.78,"freqPct":6.2},{"source":"item_9421","target":"resource_2057","name":"Subject","isShared":true,"idf":2.37,"freqPct":9.3},{"source":"item_9421","target":"resource_2752","name":"Subject","isShared":true,"idf":3.0,"freqPct":5.0},{"source":"item_9421","target":"resource_2657","name":"Subject","isShared":true,"idf":2.78,"freqPct":6.2},{"source":"item_9421","target":"resource_2825","name":"Subject","isShared":true,"idf":2.71,"freqPct":6.6},{"source":"item_9421","target":"resource_215","name":"collector","isShared":true,"idf":2.79,"freqPct":6.2},{"source":"item_9421","target":"resource_1796","name":"Is Part Of","isShared":true,"idf":2.5,"freqPct":8.2},{"source":"item_9421","target":"resource_1956","name":"Spatial Coverage","isShared":true,"idf":2.78,"freqPct":6.2},{"source":"item_9422","target":"resource_2243","name":"Subject","isShared":true,"idf":2.79,"freqPct":6.2},{"source":"item_9422","target":"resource_2024","name":"Subject","isShared":true,"idf":2.79,"freqPct":6.2},{"source":"item_9422","target":"resource_2237","name":"Subject","isShared":true,"idf":2.78,"freqPct":6.2},{"source":"item_9422","target":"resource_2057","name":"Subject","isShared":true,"idf":2.37,"freqPct":9.3},{"source":"item_9422","target":"resource_2752","name":"Subject","isShared":true,"idf":3.0,"freqPct":5.0},{"source":"item_9422","target":"resource_2657","name":"Subject","isShared":true,"idf":2.78,"freqPct":6.2},{"source":"item_9422","target":"resource_2825","name":"Subject","isShared":true,"idf":2.71,"freqPct":6.6},{"source":"item_9422","target":"resource_215","name":"collector","isShared":true,"idf":2.79,"freqPct":6.2},{"source":"item_9422","target":"resource_1796","name":"Is Part Of","isShared":true,"idf":2.5,"freqPct":8.2},{"source":"item_9422","target":"resource_1956","name":"Spatial Coverage","isShared":true,"idf":2.78,"freqPct":6.2},{"source":"item_9423","target":"resource_2243","name":"Subject","isShared":true,"idf":2.79,"freqPct":6.2},{"source":"item_9423","target":"resource_2024","name":"Subject","isShared":true,"idf":2.79,"freqPct":6.2},{"source":"item_9423","target":"resource_2237","name":"Subject","isShared":true,"idf":2.78,"freqPct":6.2},{"source":"item_9423","target":"resource_2057","name":"Subject","isShared":true,"idf":2.37,"freqPct":9.3},{"source":"item_9423","target":"resource_2752","name":"Subject","isShared":true,"idf":3.0,"freqPct":5.0},{"source":"item_9423","target":"resource_2657","name":"Subject","isShared":true,"idf":2.78,"freqPct":6.2},{"source":"item_9423","target":"resource_2825","name":"Subject","isShared":true,"idf":2.71,"freqPct":6.6},{"source":"item_9423","target":"resource_215","name":"collector","isShared":true,"idf":2.79,"freqPct":6.2},{"source":"item_9423","target":"resource_1796","name":"Is Part Of","isShared":true,"idf":2.5,"freqPct":8.2},{"source":"item_9423","target":"resource_1956","name":"Spatial Coverage","isShared":true,"idf":2.78,"freqPct":6.2},{"source":"item_9424","target":"resource_2243","name":"Subject","isShared":true,"idf":2.79,"freqPct":6.2},{"source":"item_9424","target":"resource_2024","name":"Subject","isShared":true,"idf":2.79,"freqPct":6.2},{"source":"item_9424","target":"resource_2237","name":"Subject","isShared":true,"idf":2.78,"freqPct":6.2},{"source":"item_9424","target":"resource_2057","name":"Subject","isShared":true,"idf":2.37,"freqPct":9.3},{"source":"item_9424","target":"resource_2752","name":"Subject","isShared":true,"idf":3.0,"freqPct":5.0},{"source":"item_9424","target":"resource_2657","name":"Subject","isShared":true,"idf":2.78,"freqPct":6.2},{"source":"item_9424","target":"resource_2825","name":"Subject","isShared":true,"idf":2.71,"freqPct":6.6},{"source":"item_9424","target":"resource_215","name":"collector","isShared":true,"idf":2.79,"freqPct":6.2},{"source":"item_9424","target":"resource_1796","name":"Is Part Of","isShared":true,"idf":2.5,"freqPct":8.2},{"source":"item_9424","target":"resource_1956","name":"Spatial Coverage","isShared":true,"idf":2.78,"freqPct":6.2},{"source":"item_9425","target":"resource_2243","name":"Subject","isShared":true,"idf":2.79,"freqPct":6.2},{"source":"item_9425","target":"resource_2024","name":"Subject","isShared":true,"idf":2.79,"freqPct":6.2},{"source":"item_9425","target":"resource_2237","name":"Subject","isShared":true,"idf":2.78,"freqPct":6.2},{"source":"item_9425","target":"resource_2057","name":"Subject","isShared":true,"idf":2.37,"freqPct":9.3},{"source":"item_9425","target":"resource_2752","name":"Subject","isShared":true,"idf":3.0,"freqPct":5.0},{"source":"item_9425","target":"resource_2657","name":"Subject","isShared":true,"idf":2.78,"freqPct":6.2},{"source":"item_9425","target":"resource_2825","name":"Subject","isShared":true,"idf":2.71,"freqPct":6.6},{"source":"item_9425","target":"resource_215","name":"collector","isShared":true,"idf":2.79,"freqPct":6.2},{"source":"item_9425","target":"resource_1796","name":"Is Part Of","isShared":true,"idf":2.5,"freqPct":8.2},{"source":"item_9425","target":"resource_1956","name":"Spatial Coverage","isShared":true,"idf":2.78,"freqPct":6.2},{"source":"item_9426","target":"resource_2243","name":"Subject","isShared":true,"idf":2.79,"freqPct":6.2},{"source":"item_9426","target":"resource_2024","name":"Subject","isShared":true,"idf":2.79,"freqPct":6.2},{"source":"item_9426","target":"resource_2237","name":"Subject","isShared":true,"idf":2.78,"freqPct":6.2},{"source":"item_9426","target":"resource_2057","name":"Subject","isShared":true,"idf":2.37,"freqPct":9.3},{"source":"item_9426","target":"resource_2752","name":"Subject","isShared":true,"idf":3.0,"freqPct":5.0},{"source":"item_9426","target":"resource_2657","name":"Subject","isShared":true,"idf":2.78,"freqPct":6.2},{"source":"item_9426","target":"resource_2825","name":"Subject","isShared":true,"idf":2.71,"freqPct":6.6},{"source":"item_9426","target":"resource_215","name":"collector","isShared":true,"idf":2.79,"freqPct":6.2},{"source":"item_9426","target":"resource_1796","name":"Is Part Of","isShared":true,"idf":2.5,"freqPct":8.2},{"source":"item_9426","target":"resource_1956","name":"Spatial Coverage","isShared":true,"idf":2.78,"freqPct":6.2},{"source":"item_9427","target":"resource_2243","name":"Subject","isShared":true,"idf":2.79,"freqPct":6.2},{"source":"item_9427","target":"resource_2024","name":"Subject","isShared":true,"idf":2.79,"freqPct":6.2},{"source":"item_9427","target":"resource_2237","name":"Subject","isShared":true,"idf":2.78,"freqPct":6.2},{"source":"item_9427","target":"resource_2057","name":"Subject","isShared":true,"idf":2.37,"freqPct":9.3},{"source":"item_9427","target":"resource_2752","name":"Subject","isShared":true,"idf":3.0,"freqPct":5.0},{"source":"item_9427","target":"resource_2657","name":"Subject","isShared":true,"idf":2.78,"freqPct":6.2},{"source":"item_9427","target":"resource_2825","name":"Subject","isShared":true,"idf":2.71,"freqPct":6.6},{"source":"item_9427","target":"resource_215","name":"collector","isShared":true,"idf":2.79,"freqPct":6.2},{"source":"item_9427","target":"resource_1796","name":"Is Part Of","isShared":true,"idf":2.5,"freqPct":8.2},{"source":"item_9427","target":"resource_1956","name":"Spatial Coverage","isShared":true,"idf":2.78,"freqPct":6.2},{"source":"item_9428","target":"resource_2243","name":"Subject","isShared":true,"idf":2.79,"freqPct":6.2},{"source":"item_9428","target":"resource_2024","name":"Subject","isShared":true,"idf":2.79,"freqPct":6.2},{"source":"item_9428","target":"resource_2237","name":"Subject","isShared":true,"idf":2.78,"freqPct":6.2},{"source":"item_9428","target":"resource_2057","name":"Subject","isShared":true,"idf":2.37,"freqPct":9.3},{"source":"item_9428","target":"resource_2752","name":"Subject","isShared":true,"idf":3.0,"freqPct":5.0},{"source":"item_9428","target":"resource_2657","name":"Subject","isShared":true,"idf":2.78,"freqPct":6.2},{"source":"item_9428","target":"resource_2825","name":"Subject","isShared":true,"idf":2.71,"freqPct":6.6},{"source":"item_9428","target":"resource_215","name":"collector","isShared":true,"idf":2.79,"freqPct":6.2},{"source":"item_9428","target":"resource_1796","name":"Is Part Of","isShared":true,"idf":2.5,"freqPct":8.2},{"source":"item_9428","target":"resource_1956","name":"Spatial Coverage","isShared":true,"idf":2.78,"freqPct":6.2},{"source":"item_9429","target":"resource_2243","name":"Subject","isShared":true,"idf":2.79,"freqPct":6.2},{"source":"item_9429","target":"resource_2024","name":"Subject","isShared":true,"idf":2.79,"freqPct":6.2},{"source":"item_9429","target":"resource_2237","name":"Subject","isShared":true,"idf":2.78,"freqPct":6.2},{"source":"item_9429","target":"resource_2057","name":"Subject","isShared":true,"idf":2.37,"freqPct":9.3},{"source":"item_9429","target":"resource_2752","name":"Subject","isShared":true,"idf":3.0,"freqPct":5.0},{"source":"item_9429","target":"resource_2657","name":"Subject","isShared":true,"idf":2.78,"freqPct":6.2},{"source":"item_9429","target":"resource_2825","name":"Subject","isShared":true,"idf":2.71,"freqPct":6.6},{"source":"item_9429","target":"resource_215","name":"collector","isShared":true,"idf":2.79,"freqPct":6.2},{"source":"item_9429","target":"resource_1796","name":"Is Part Of","isShared":true,"idf":2.5,"freqPct":8.2},{"source":"item_9429","target":"resource_1956","name":"Spatial Coverage","isShared":true,"idf":2.78,"freqPct":6.2},{"source":"item_9430","target":"resource_2243","name":"Subject","isShared":true,"idf":2.79,"freqPct":6.2},{"source":"item_9430","target":"resource_2024","name":"Subject","isShared":true,"idf":2.79,"freqPct":6.2},{"source":"item_9430","target":"resource_2237","name":"Subject","isShared":true,"idf":2.78,"freqPct":6.2},{"source":"item_9430","target":"resource_2057","name":"Subject","isShared":true,"idf":2.37,"freqPct":9.3},{"source":"item_9430","target":"resource_2752","name":"Subject","isShared":true,"idf":3.0,"freqPct":5.0},{"source":"item_9430","target":"resource_2657","name":"Subject","isShared":true,"idf":2.78,"freqPct":6.2},{"source":"item_9430","target":"resource_2825","name":"Subject","isShared":true,"idf":2.71,"freqPct":6.6},{"source":"item_9430","target":"resource_215","name":"collector","isShared":true,"idf":2.79,"freqPct":6.2},{"source":"item_9430","target":"resource_1796","name":"Is Part Of","isShared":true,"idf":2.5,"freqPct":8.2},{"source":"item_9430","target":"resource_1956","name":"Spatial Coverage","isShared":true,"idf":2.78,"freqPct":6.2},{"source":"item_9431","target":"resource_2243","name":"Subject","isShared":true,"idf":2.79,"freqPct":6.2},{"source":"item_9431","target":"resource_2024","name":"Subject","isShared":true,"idf":2.79,"freqPct":6.2},{"source":"item_9431","target":"resource_2237","name":"Subject","isShared":true,"idf":2.78,"freqPct":6.2},{"source":"item_9431","target":"resource_2057","name":"Subject","isShared":true,"idf":2.37,"freqPct":9.3},{"source":"item_9431","target":"resource_2752","name":"Subject","isShared":true,"idf":3.0,"freqPct":5.0},{"source":"item_9431","target":"resource_2657","name":"Subject","isShared":true,"idf":2.78,"freqPct":6.2},{"source":"item_9431","target":"resource_2825","name":"Subject","isShared":true,"idf":2.71,"freqPct":6.6},{"source":"item_9431","target":"resource_215","name":"collector","isShared":true,"idf":2.79,"freqPct":6.2},{"source":"item_9431","target":"resource_1796","name":"Is Part Of","isShared":true,"idf":2.5,"freqPct":8.2},{"source":"item_9431","target":"resource_1956","name":"Spatial Coverage","isShared":true,"idf":2.78,"freqPct":6.2},{"source":"item_9432","target":"resource_2243","name":"Subject","isShared":true,"idf":2.79,"freqPct":6.2},{"source":"item_9432","target":"resource_2024","name":"Subject","isShared":true,"idf":2.79,"freqPct":6.2},{"source":"item_9432","target":"resource_2237","name":"Subject","isShared":true,"idf":2.78,"freqPct":6.2},{"source":"item_9432","target":"resource_2057","name":"Subject","isShared":true,"idf":2.37,"freqPct":9.3},{"source":"item_9432","target":"resource_2752","name":"Subject","isShared":true,"idf":3.0,"freqPct":5.0},{"source":"item_9432","target":"resource_2657","name":"Subject","isShared":true,"idf":2.78,"freqPct":6.2},{"source":"item_9432","target":"resource_2825","name":"Subject","isShared":true,"idf":2.71,"freqPct":6.6},{"source":"item_9432","target":"resource_215","name":"collector","isShared":true,"idf":2.79,"freqPct":6.2},{"source":"item_9432","target":"resource_1796","name":"Is Part Of","isShared":true,"idf":2.5,"freqPct":8.2},{"source":"item_9432","target":"resource_1956","name":"Spatial Coverage","isShared":true,"idf":2.78,"freqPct":6.2},{"source":"item_9433","target":"resource_2243","name":"Subject","isShared":true,"idf":2.79,"freqPct":6.2},{"source":"item_9433","target":"resource_2024","name":"Subject","isShared":true,"idf":2.79,"freqPct":6.2},{"source":"item_9433","target":"resource_2237","name":"Subject","isShared":true,"idf":2.78,"freqPct":6.2},{"source":"item_9433","target":"resource_2057","name":"Subject","isShared":true,"idf":2.37,"freqPct":9.3},{"source":"item_9433","target":"resource_2752","name":"Subject","isShared":true,"idf":3.0,"freqPct":5.0},{"source":"item_9433","target":"resource_2657","name":"Subject","isShared":true,"idf":2.78,"freqPct":6.2},{"source":"item_9433","target":"resource_2825","name":"Subject","isShared":true,"idf":2.71,"freqPct":6.6},{"source":"item_9433","target":"resource_215","name":"collector","isShared":true,"idf":2.79,"freqPct":6.2},{"source":"item_9433","target":"resource_1796","name":"Is Part Of","isShared":true,"idf":2.5,"freqPct":8.2},{"source":"item_9433","target":"resource_1956","name":"Spatial Coverage","isShared":true,"idf":2.78,"freqPct":6.2},{"source":"item_9434","target":"resource_2243","name":"Subject","isShared":true,"idf":2.79,"freqPct":6.2},{"source":"item_9434","target":"resource_2024","name":"Subject","isShared":true,"idf":2.79,"freqPct":6.2},{"source":"item_9434","target":"resource_2237","name":"Subject","isShared":true,"idf":2.78,"freqPct":6.2},{"source":"item_9434","target":"resource_2057","name":"Subject","isShared":true,"idf":2.37,"freqPct":9.3},{"source":"item_9434","target":"resource_2752","name":"Subject","isShared":true,"idf":3.0,"freqPct":5.0},{"source":"item_9434","target":"resource_2657","name":"Subject","isShared":true,"idf":2.78,"freqPct":6.2},{"source":"item_9434","target":"resource_2825","name":"Subject","isShared":true,"idf":2.71,"freqPct":6.6},{"source":"item_9434","target":"resource_215","name":"collector","isShared":true,"idf":2.79,"freqPct":6.2},{"source":"item_9434","target":"resource_1796","name":"Is Part Of","isShared":true,"idf":2.5,"freqPct":8.2},{"source":"item_9434","target":"resource_1956","name":"Spatial Coverage","isShared":true,"idf":2.78,"freqPct":6.2},{"source":"item_9435","target":"resource_2243","name":"Subject","isShared":true,"idf":2.79,"freqPct":6.2},{"source":"item_9435","target":"resource_2024","name":"Subject","isShared":true,"idf":2.79,"freqPct":6.2},{"source":"item_9435","target":"resource_2237","name":"Subject","isShared":true,"idf":2.78,"freqPct":6.2},{"source":"item_9435","target":"resource_2057","name":"Subject","isShared":true,"idf":2.37,"freqPct":9.3},{"source":"item_9435","target":"resource_2752","name":"Subject","isShared":true,"idf":3.0,"freqPct":5.0},{"source":"item_9435","target":"resource_2657","name":"Subject","isShared":true,"idf":2.78,"freqPct":6.2},{"source":"item_9435","target":"resource_2825","name":"Subject","isShared":true,"idf":2.71,"freqPct":6.6},{"source":"item_9435","target":"resource_215","name":"collector","isShared":true,"idf":2.79,"freqPct":6.2},{"source":"item_9435","target":"resource_1796","name":"Is Part Of","isShared":true,"idf":2.5,"freqPct":8.2},{"source":"item_9435","target":"resource_1956","name":"Spatial Coverage","isShared":true,"idf":2.78,"freqPct":6.2},{"source":"item_9436","target":"resource_2243","name":"Subject","isShared":true,"idf":2.79,"freqPct":6.2},{"source":"item_9436","target":"resource_2024","name":"Subject","isShared":true,"idf":2.79,"freqPct":6.2},{"source":"item_9436","target":"resource_2237","name":"Subject","isShared":true,"idf":2.78,"freqPct":6.2},{"source":"item_9436","target":"resource_2057","name":"Subject","isShared":true,"idf":2.37,"freqPct":9.3},{"source":"item_9436","target":"resource_2752","name":"Subject","isShared":true,"idf":3.0,"freqPct":5.0},{"source":"item_9436","target":"resource_2657","name":"Subject","isShared":true,"idf":2.78,"freqPct":6.2},{"source":"item_9436","target":"resource_2825","name":"Subject","isShared":true,"idf":2.71,"freqPct":6.6},{"source":"item_9436","target":"resource_215","name":"collector","isShared":true,"idf":2.79,"freqPct":6.2},{"source":"item_9436","target":"resource_1796","name":"Is Part Of","isShared":true,"idf":2.5,"freqPct":8.2},{"source":"item_9436","target":"resource_1956","name":"Spatial Coverage","isShared":true,"idf":2.78,"freqPct":6.2},{"source":"item_9437","target":"resource_2243","name":"Subject","isShared":true,"idf":2.79,"freqPct":6.2},{"source":"item_9437","target":"resource_2024","name":"Subject","isShared":true,"idf":2.79,"freqPct":6.2},{"source":"item_9437","target":"resource_2237","name":"Subject","isShared":true,"idf":2.78,"freqPct":6.2},{"source":"item_9437","target":"resource_2057","name":"Subject","isShared":true,"idf":2.37,"freqPct":9.3},{"source":"item_9437","target":"resource_2752","name":"Subject","isShared":true,"idf":3.0,"freqPct":5.0},{"source":"item_9437","target":"resource_2657","name":"Subject","isShared":true,"idf":2.78,"freqPct":6.2},{"source":"item_9437","target":"resource_2825","name":"Subject","isShared":true,"idf":2.71,"freqPct":6.6},{"source":"item_9437","target":"resource_215","name":"collector","isShared":true,"idf":2.79,"freqPct":6.2},{"source":"item_9437","target":"resource_1796","name":"Is Part Of","isShared":true,"idf":2.5,"freqPct":8.2},{"source":"item_9437","target":"resource_1956","name":"Spatial Coverage","isShared":true,"idf":2.78,"freqPct":6.2},{"source":"item_9438","target":"resource_2243","name":"Subject","isShared":true,"idf":2.79,"freqPct":6.2},{"source":"item_9438","target":"resource_2024","name":"Subject","isShared":true,"idf":2.79,"freqPct":6.2},{"source":"item_9438","target":"resource_2237","name":"Subject","isShared":true,"idf":2.78,"freqPct":6.2},{"source":"item_9438","target":"resource_2057","name":"Subject","isShared":true,"idf":2.37,"freqPct":9.3},{"source":"item_9438","target":"resource_2752","name":"Subject","isShared":true,"idf":3.0,"freqPct":5.0},{"source":"item_9438","target":"resource_2657","name":"Subject","isShared":true,"idf":2.78,"freqPct":6.2},{"source":"item_9438","target":"resource_2825","name":"Subject","isShared":true,"idf":2.71,"freqPct":6.6},{"source":"item_9438","target":"resource_215","name":"collector","isShared":true,"idf":2.79,"freqPct":6.2},{"source":"item_9438","target":"resource_1796","name":"Is Part Of","isShared":true,"idf":2.5,"freqPct":8.2},{"source":"item_9438","target":"resource_1956","name":"Spatial Coverage","isShared":true,"idf":2.78,"freqPct":6.2},{"source":"item_9439","target":"resource_2243","name":"Subject","isShared":true,"idf":2.79,"freqPct":6.2},{"source":"item_9439","target":"resource_2024","name":"Subject","isShared":true,"idf":2.79,"freqPct":6.2},{"source":"item_9439","target":"resource_2237","name":"Subject","isShared":true,"idf":2.78,"freqPct":6.2},{"source":"item_9439","target":"resource_2057","name":"Subject","isShared":true,"idf":2.37,"freqPct":9.3},{"source":"item_9439","target":"resource_2752","name":"Subject","isShared":true,"idf":3.0,"freqPct":5.0},{"source":"item_9439","target":"resource_2657","name":"Subject","isShared":true,"idf":2.78,"freqPct":6.2},{"source":"item_9439","target":"resource_2825","name":"Subject","isShared":true,"idf":2.71,"freqPct":6.6},{"source":"item_9439","target":"resource_215","name":"collector","isShared":true,"idf":2.79,"freqPct":6.2},{"source":"item_9439","target":"resource_1796","name":"Is Part Of","isShared":true,"idf":2.5,"freqPct":8.2},{"source":"item_9439","target":"resource_1956","name":"Spatial Coverage","isShared":true,"idf":2.78,"freqPct":6.2},{"source":"item_9443","target":"resource_2243","name":"Subject","isShared":true,"idf":2.79,"freqPct":6.2},{"source":"item_9443","target":"resource_2024","name":"Subject","isShared":true,"idf":2.79,"freqPct":6.2},{"source":"item_9443","target":"resource_2237","name":"Subject","isShared":true,"idf":2.78,"freqPct":6.2},{"source":"item_9443","target":"resource_2057","name":"Subject","isShared":true,"idf":2.37,"freqPct":9.3},{"source":"item_9443","target":"resource_2752","name":"Subject","isShared":true,"idf":3.0,"freqPct":5.0},{"source":"item_9443","target":"resource_2657","name":"Subject","isShared":true,"idf":2.78,"freqPct":6.2},{"source":"item_9443","target":"resource_2825","name":"Subject","isShared":true,"idf":2.71,"freqPct":6.6},{"source":"item_9443","target":"resource_215","name":"collector","isShared":true,"idf":2.79,"freqPct":6.2},{"source":"item_9443","target":"resource_1796","name":"Is Part Of","isShared":true,"idf":2.5,"freqPct":8.2},{"source":"item_9443","target":"resource_1956","name":"Spatial Coverage","isShared":true,"idf":2.78,"freqPct":6.2},{"source":"item_9444","target":"resource_2243","name":"Subject","isShared":true,"idf":2.79,"freqPct":6.2},{"source":"item_9444","target":"resource_2024","name":"Subject","isShared":true,"idf":2.79,"freqPct":6.2},{"source":"item_9444","target":"resource_2237","name":"Subject","isShared":true,"idf":2.78,"freqPct":6.2},{"source":"item_9444","target":"resource_2057","name":"Subject","isShared":true,"idf":2.37,"freqPct":9.3},{"source":"item_9444","target":"resource_2752","name":"Subject","isShared":true,"idf":3.0,"freqPct":5.0},{"source":"item_9444","target":"resource_2657","name":"Subject","isShared":true,"idf":2.78,"freqPct":6.2},{"source":"item_9444","target":"resource_2825","name":"Subject","isShared":true,"idf":2.71,"freqPct":6.6},{"source":"item_9444","target":"resource_215","name":"collector","isShared":true,"idf":2.79,"freqPct":6.2},{"source":"item_9444","target":"resource_1796","name":"Is Part Of","isShared":true,"idf":2.5,"freqPct":8.2},{"source":"item_9444","target":"resource_1956","name":"Spatial Coverage","isShared":true,"idf":2.78,"freqPct":6.2}],"categories":[{"name":"Item"},{"name":"Contributor"},{"name":"Subject"},{"name":"Project"},{"name":"Location"},{"name":"Institution"},{"name":"Genre"},{"name":"Shared Item"}],"stats":{"maxStrength":31.15,"maxFreqPct":9.3},"itemMap":{"origins":[{"name":"London","lat":51.507222222,"lon":-0.1275,"itemId":1956}],"current":[]}}